[{"country":"BZ","name":"San pedro town","admin1Code":"BZ.01","latitude":17.91598,"longitude":-87.9659,"translations":{"pt":"San pedro town","it":"San pedro town","ru":"Сан-педро","uk":"San pedro town","de":"San pedro town","es":"San pedro town","en":"San pedro town","fr":"San pedro town"}},{"country":"BZ","name":"San ignacio","admin1Code":"BZ.02","latitude":17.1588,"longitude":-89.0696,"translations":{"pt":"San ignacio","it":"San ignacio","ru":"Сан-игнасио","uk":"Сан-ігнасіо-кайо","de":"San ignacio","es":"San ignacio","en":"San ignacio","fr":"San ignacio"}},{"country":"BZ","name":"Orange walk","admin1Code":"BZ.04","latitude":18.08124,"longitude":-88.56328,"translations":{"pt":"Orange walk","it":"Orange walk","ru":"Ориндж-уолк","uk":"Orange walk","de":"Orange walk","es":"Orange walk","en":"Orange walk","fr":"Orange walk"}},{"country":"BZ","name":"Belmopan","admin1Code":"BZ.02","latitude":17.25,"longitude":-88.76667,"translations":{"pt":"Belmopan","it":"Belmopan","ru":"Бельмопан","uk":"Бельмопан","de":"Belmopan","es":"Belmopán","en":"Belmopan","fr":"Belmopan"}},{"country":"BZ","name":"Belize city","admin1Code":"BZ.01","latitude":17.49952,"longitude":-88.19756,"translations":{"pt":"Belize","it":"Belize city","ru":"Белиз","uk":"Беліз","de":"Belize city","es":"Ciudad de belice","en":"Belize city","fr":"Belize city"}}]