[{"country":"PL","name":"Żyrardów","admin1Code":"PL.78","latitude":52.0488,"longitude":20.44599,"translations":{"pt":"Żyrardów","it":"Żyrardów","ru":"Жирардув","uk":"Жирардув","de":"Żyrardów","es":"Żyrardów","en":"Żyrardów","fr":"Żyrardów"}},{"country":"PL","name":"Żoliborz","admin1Code":"PL.78","latitude":52.26896,"longitude":20.98644,"translations":{"pt":"Żoliborz","it":"Żoliborz","ru":"Жолибож","uk":"Жолібож","de":"Żoliborz","es":"Żoliborz","en":"Żoliborz","fr":"Żoliborz"}},{"country":"PL","name":"Zielonka","admin1Code":"PL.78","latitude":52.30376,"longitude":21.16018,"translations":{"pt":"Zielonka","it":"Zielonka","ru":"Зеленка","uk":"Зельонка","de":"Zielonka","es":"Zielonka","en":"Zielonka","fr":"Zielonka"}},{"country":"PL","name":"Zamość","admin1Code":"PL.75","latitude":50.72314,"longitude":23.25196,"translations":{"pt":"Zamość","it":"Zamość","ru":"Замосць","uk":"Замостя","de":"Zamość","es":"Zamość","en":"Zamość","fr":"Zamość"}},{"country":"PL","name":"Zambrów","admin1Code":"PL.81","latitude":52.9855,"longitude":22.24319,"translations":{"pt":"Zambrów","it":"Zambrów","ru":"Замбрув","uk":"Замбрув","de":"Zambrów","es":"Zambrów","en":"Zambrów","fr":"Zambrów"}},{"country":"PL","name":"Ząbki","admin1Code":"PL.78","latitude":52.29271,"longitude":21.10539,"translations":{"pt":"Ząbki","it":"Ząbki","ru":"Зомбки","uk":"Зомбки","de":"Ząbki","es":"Ząbki","en":"Ząbki","fr":"Ząbki"}},{"country":"PL","name":"Wyszków","admin1Code":"PL.78","latitude":52.59278,"longitude":21.4584,"translations":{"pt":"Wyszków","it":"Wyszków","ru":"Вышкув","uk":"Вишкув","de":"Wyszków","es":"Wyszków","en":"Wyszków","fr":"Wyszków"}},{"country":"PL","name":"Wołomin","admin1Code":"PL.78","latitude":52.34006,"longitude":21.24207,"translations":{"pt":"Wołomin","it":"Wołomin","ru":"Воломин","uk":"Воломін","de":"Wołomin","es":"Wołomin","en":"Wołomin","fr":"Wołomin"}},{"country":"PL","name":"Воля","admin1Code":"PL.78","latitude":52.23477,"longitude":20.96004,"translations":{"pt":"Volja","it":"Volja","ru":"Воля","uk":"Воля","de":"Volja","es":"Volja","en":"Volja","fr":"Volja"}},{"country":"PL","name":"Włochy","admin1Code":"PL.78","latitude":52.17941,"longitude":20.94612,"translations":{"pt":"Włochy","it":"Włochy","ru":"Włochy","uk":"Włochy","de":"Włochy","es":"Włochy","en":"Włochy","fr":"Włochy"}},{"country":"PL","name":"Wieliczka","admin1Code":"PL.77","latitude":49.98738,"longitude":20.06473,"translations":{"pt":"Wieliczka","it":"Wieliczka","ru":"Величка","uk":"Величка","de":"Wieliczka","es":"Wieliczka","en":"Wieliczka","fr":"Wieliczka"}},{"country":"PL","name":"Wesoła","admin1Code":"PL.78","latitude":52.25451,"longitude":21.22407,"translations":{"pt":"Wesoła","it":"Wesoła","ru":"Wesoła","uk":"Wesoła","de":"Wesoła","es":"Wesoła","en":"Wesoła","fr":"Wesoła"}},{"country":"PL","name":"Wawer","admin1Code":"PL.78","latitude":52.19656,"longitude":21.17752,"translations":{"pt":"Wawer","it":"Wawer","ru":"Wawer","uk":"Wawer","de":"Wawer","es":"Wawer","en":"Wawer","fr":"Wawer"}},{"country":"PL","name":"Warsaw","admin1Code":"PL.78","latitude":52.22977,"longitude":21.01178,"translations":{"pt":"Varsóvia","it":"Varsavia","ru":"Варшава","uk":"Варшава","de":"Warschau","es":"Varsovia","en":"Warsaw","fr":"Varsovie"}},{"country":"PL","name":"Ursus","admin1Code":"PL.78","latitude":52.19517,"longitude":20.88419,"translations":{"pt":"Ursus","it":"Ursus","ru":"Урсус","uk":"Урсус","de":"Ursus","es":"Ursus","en":"Ursus","fr":"Ursus"}},{"country":"PL","name":"Tomaszów mazowiecki","admin1Code":"PL.74","latitude":51.53131,"longitude":20.00855,"translations":{"pt":"Tomaszów mazowiecki","it":"Tomaszów mazowiecki","ru":"Томашув-мазовецкий","uk":"Томашув-мазовецький","de":"Tomaszów mazowiecki","es":"Tomaszów mazowiecki","en":"Tomaszów mazowiecki","fr":"Tomaszów mazowiecki"}},{"country":"PL","name":"Томашув-любельски","admin1Code":"PL.75","latitude":50.44767,"longitude":23.41616,"translations":{"pt":"Tomashuv-ljubel'sky","it":"Tomashuv-ljubel'sky","ru":"Томашув-любельски","uk":"Томашів","de":"Tomashuv-ljubel'sky","es":"Tomashuv-ljubel'sky","en":"Tomashuv-ljubel'sky","fr":"Tomashuv-ljubel'sky"}},{"country":"PL","name":"Tarnów","admin1Code":"PL.77","latitude":50.01381,"longitude":20.98698,"translations":{"pt":"Tarnów","it":"Tarnów","ru":"Тарнув","uk":"Тарнув","de":"Tarnów","es":"Tarnów","en":"Tarnów","fr":"Tarnów"}},{"country":"PL","name":"Tarnobrzeg","admin1Code":"PL.80","latitude":50.57304,"longitude":21.67937,"translations":{"pt":"Tarnobrzeg","it":"Tarnobrzeg","ru":"Тарнобжеге","uk":"Тарнобжег","de":"Tarnobrzeg","es":"Tarnobrzeg","en":"Tarnobrzeg","fr":"Tarnobrzeg"}},{"country":"PL","name":"Таргувек","admin1Code":"PL.78","latitude":52.29185,"longitude":21.04845,"translations":{"pt":"Tarhuvek","it":"Tarhuvek","ru":"Таргувек","uk":"Таргувек","de":"Tarhuvek","es":"Tarhuvek","en":"Tarhuvek","fr":"Tarhuvek"}},{"country":"PL","name":"Ortelsburg","admin1Code":"PL.85","latitude":53.56259,"longitude":20.98747,"translations":{"pt":"Ortelsburg","it":"Ortelsburg","ru":"Щитно","uk":"Щитно","de":"Ortelsburg","es":"Ortelsburg","en":"Ortelsburg","fr":"Ortelsburg"}},{"country":"PL","name":"Świdnik","admin1Code":"PL.75","latitude":51.21898,"longitude":22.69621,"translations":{"pt":"Świdnik","it":"Świdnik","ru":"Świdnik","uk":"Świdnik","de":"Świdnik","es":"Świdnik","en":"Świdnik","fr":"Świdnik"}},{"country":"PL","name":"Suwałki","admin1Code":"PL.81","latitude":54.11175,"longitude":22.93087,"translations":{"pt":"Suwałki","it":"Suwałki","ru":"Сувалки","uk":"Сувалки","de":"Suwałki","es":"Suwałki","en":"Suwałki","fr":"Suwałki"}},{"country":"PL","name":"Сулеювек","admin1Code":"PL.78","latitude":52.25221,"longitude":21.26902,"translations":{"pt":"Sulejuvek","it":"Sulejuvek","ru":"Сулеювек","uk":"Сулеювек","de":"Sulejuvek","es":"Sulejuvek","en":"Sulejuvek","fr":"Sulejuvek"}},{"country":"PL","name":"Сташув","admin1Code":"PL.84","latitude":50.56307,"longitude":21.16593,"translations":{"pt":"Stashuv","it":"Stashuv","ru":"Сташув","uk":"Сташув","de":"Stashuv","es":"Stashuv","en":"Stashuv","fr":"Stashuv"}},{"country":"PL","name":"Starachowice","admin1Code":"PL.84","latitude":51.0374,"longitude":21.07126,"translations":{"pt":"Starachowice","it":"Starachowice","ru":"Стараховице","uk":"Стараховіце","de":"Starachowice","es":"Starachowice","en":"Starachowice","fr":"Starachowice"}},{"country":"PL","name":"Stalowa wola","admin1Code":"PL.80","latitude":50.58286,"longitude":22.05334,"translations":{"pt":"Stalowa wola","it":"Stalowa wola","ru":"Сталёва-воля","uk":"Стальова воля","de":"Stalowa wola","es":"Stalowa wola","en":"Stalowa wola","fr":"Stalowa wola"}},{"country":"PL","name":"Śródmieście","admin1Code":"PL.78","latitude":52.22904,"longitude":21.01644,"translations":{"pt":"Śródmieście","it":"Śródmieście","ru":"Средместье","uk":"Середмістя","de":"Śródmieście","es":"Śródmieście","en":"Śródmieście","fr":"Śródmieście"}},{"country":"PL","name":"Sokołów podlaski","admin1Code":"PL.78","latitude":52.40677,"longitude":22.25307,"translations":{"pt":"Sokołów podlaski","it":"Sokołów podlaski","ru":"Соколув-подляски","uk":"Соколув-підляський","de":"Sokołów podlaski","es":"Sokołów podlaski","en":"Sokołów podlaski","fr":"Sokołów podlaski"}},{"country":"PL","name":"Sokółka","admin1Code":"PL.81","latitude":53.40715,"longitude":23.50228,"translations":{"pt":"Sokółka","it":"Sokółka","ru":"Сокулка","uk":"Сокулка","de":"Sokółka","es":"Sokółka","en":"Sokółka","fr":"Sokółka"}},{"country":"PL","name":"Сохачев","admin1Code":"PL.78","latitude":52.22944,"longitude":20.23838,"translations":{"pt":"Sokhachev","it":"Sokhachev","ru":"Сохачев","uk":"Сохачев","de":"Sokhachev","es":"Sokhachev","en":"Sokhachev","fr":"Sokhachev"}},{"country":"PL","name":"Skierniewice","admin1Code":"PL.74","latitude":51.95485,"longitude":20.15837,"translations":{"pt":"Skierniewice","it":"Skierniewice","ru":"Скерневице","uk":"Скерневіце","de":"Skierniewice","es":"Skierniewice","en":"Skierniewice","fr":"Skierniewice"}},{"country":"PL","name":"Скаржиско-каменна","admin1Code":"PL.84","latitude":51.11311,"longitude":20.87162,"translations":{"pt":"Skarzhysko-kamenna","it":"Skarzhysko-kamenna","ru":"Скаржиско-каменна","uk":"Скаржисько-каменна","de":"Skarzhysko-kamenna","es":"Skarzhysko-kamenna","en":"Skarzhysko-kamenna","fr":"Skarzhysko-kamenna"}},{"country":"PL","name":"Siemiatycze","admin1Code":"PL.81","latitude":52.42719,"longitude":22.86231,"translations":{"pt":"Siemiatycze","it":"Siemiatycze","ru":"Семятыче","uk":"Сімятичі","de":"Siemiatycze","es":"Siemiatycze","en":"Siemiatycze","fr":"Siemiatycze"}},{"country":"PL","name":"Siedlce","admin1Code":"PL.78","latitude":52.16772,"longitude":22.29006,"translations":{"pt":"Siedlce","it":"Siedlce","ru":"Седльце","uk":"Седльце","de":"Siedlce","es":"Siedlce","en":"Siedlce","fr":"Siedlce"}},{"country":"PL","name":"Sanok","admin1Code":"PL.80","latitude":49.55573,"longitude":22.2056,"translations":{"pt":"Sanok","it":"Sanok","ru":"Санок","uk":"Сянік","de":"Sanok","es":"Sanok","en":"Sanok","fr":"Sanok"}},{"country":"PL","name":"Sandomierz","admin1Code":"PL.84","latitude":50.68265,"longitude":21.74898,"translations":{"pt":"Sandomierz","it":"Sandomierz","ru":"Сандомир","uk":"Сандомир","de":"Sandomierz","es":"Sandomierz","en":"Sandomierz","fr":"Sandomierz"}},{"country":"PL","name":"Rzeszów","admin1Code":"PL.80","latitude":50.04132,"longitude":21.99901,"translations":{"pt":"Rzeszów","it":"Rzeszów","ru":"Жешув","uk":"Ряшів","de":"Rzeszów","es":"Rzeszów","en":"Rzeszów","fr":"Rzeszów"}},{"country":"PL","name":"Ропчице","admin1Code":"PL.80","latitude":50.05229,"longitude":21.60891,"translations":{"pt":"Ropchytse","it":"Ropchytse","ru":"Ропчице","uk":"Ропчице","de":"Ropchytse","es":"Ropchytse","en":"Ropchytse","fr":"Ropchytse"}},{"country":"PL","name":"Rembertów","admin1Code":"PL.78","latitude":52.26059,"longitude":21.16355,"translations":{"pt":"Rembertów","it":"Rembertów","ru":"Рембертув","uk":"Рембертув","de":"Rembertów","es":"Rembertów","en":"Rembertów","fr":"Rembertów"}},{"country":"PL","name":"Рава-мазовецька","admin1Code":"PL.74","latitude":51.76437,"longitude":20.25493,"translations":{"pt":"Rava-mazovets'ka","it":"Rava-mazovets'ka","ru":"Рава-мазовецкая","uk":"Рава-мазовецька","de":"Rava-mazovets'ka","es":"Rava-mazovets'ka","en":"Rava-mazovets'ka","fr":"Rava-mazovets'ka"}},{"country":"PL","name":"Радинь-підляський","admin1Code":"PL.75","latitude":51.78333,"longitude":22.61667,"translations":{"pt":"Radyn'-pidljas'kyj","it":"Radyn'-pidljas'kyj","ru":"Радзынь-подляский","uk":"Радинь-підляський","de":"Radyn'-pidljas'kyj","es":"Radyn'-pidljas'kyj","en":"Radyn'-pidljas'kyj","fr":"Radyn'-pidljas'kyj"}},{"country":"PL","name":"Radom","admin1Code":"PL.78","latitude":51.40253,"longitude":21.14714,"translations":{"pt":"Radom","it":"Radom","ru":"Радом","uk":"Радом","de":"Radom","es":"Radom","en":"Radom","fr":"Radom"}},{"country":"PL","name":"Pułtusk","admin1Code":"PL.78","latitude":52.7025,"longitude":21.08276,"translations":{"pt":"Pułtusk","it":"Pułtusk","ru":"Пултуск","uk":"Пултуськ","de":"Pułtusk","es":"Pułtusk","en":"Pułtusk","fr":"Pułtusk"}},{"country":"PL","name":"Puławy","admin1Code":"PL.75","latitude":51.41655,"longitude":21.96939,"translations":{"pt":"Puławy","it":"Puławy","ru":"Пулавы","uk":"Пулави","de":"Puławy","es":"Puławy","en":"Puławy","fr":"Puławy"}},{"country":"PL","name":"Przeworsk","admin1Code":"PL.80","latitude":50.05912,"longitude":22.49408,"translations":{"pt":"Przeworsk","it":"Przeworsk","ru":"Пшеворск","uk":"Переворськ","de":"Przeworsk","es":"Przeworsk","en":"Przeworsk","fr":"Przeworsk"}},{"country":"PL","name":"Перемишль","admin1Code":"PL.80","latitude":49.78498,"longitude":22.76728,"translations":{"pt":"Peremyshl'","it":"Peremyshl'","ru":"Перемышль","uk":"Перемишль","de":"Peremyshl'","es":"Peremyshl'","en":"Peremyshl'","fr":"Peremyshl'"}},{"country":"PL","name":"Przasnysz","admin1Code":"PL.78","latitude":53.01907,"longitude":20.88029,"translations":{"pt":"Przasnysz","it":"Przasnysz","ru":"Пшасныш","uk":"Пшасниш","de":"Przasnysz","es":"Przasnysz","en":"Przasnysz","fr":"Przasnysz"}},{"country":"PL","name":"Pruszków","admin1Code":"PL.78","latitude":52.17072,"longitude":20.81214,"translations":{"pt":"Pruszków","it":"Pruszków","ru":"Прушкув","uk":"Прушкув","de":"Pruszków","es":"Pruszków","en":"Pruszków","fr":"Pruszków"}},{"country":"PL","name":"Płońsk","admin1Code":"PL.78","latitude":52.62348,"longitude":20.37552,"translations":{"pt":"Płońsk","it":"Płońsk","ru":"Плоньск","uk":"Плонськ","de":"Płońsk","es":"Płońsk","en":"Płońsk","fr":"Płońsk"}},{"country":"PL","name":"Pisz","admin1Code":"PL.85","latitude":53.62744,"longitude":21.81253,"translations":{"pt":"Pisz","it":"Pisz","ru":"Пиш","uk":"Піш","de":"Pisz","es":"Pisz","en":"Pisz","fr":"Pisz"}},{"country":"PL","name":"Пйонкі","admin1Code":"PL.78","latitude":51.47604,"longitude":21.44995,"translations":{"pt":"Pjonki","it":"Pjonki","ru":"Пёнки","uk":"Пйонкі","de":"Pjonki","es":"Pjonki","en":"Pjonki","fr":"Pjonki"}},{"country":"PL","name":"Пястув","admin1Code":"PL.78","latitude":52.18435,"longitude":20.83952,"translations":{"pt":"Pjastuv","it":"Pjastuv","ru":"Пястув","uk":"Пястув","de":"Pjastuv","es":"Pjastuv","en":"Pjastuv","fr":"Pjastuv"}},{"country":"PL","name":"Piaseczno","admin1Code":"PL.78","latitude":52.0814,"longitude":21.02397,"translations":{"pt":"Piaseczno","it":"Piaseczno","ru":"Пясечно","uk":"Пясечно","de":"Piaseczno","es":"Piaseczno","en":"Piaseczno","fr":"Piaseczno"}},{"country":"PL","name":"Otwock","admin1Code":"PL.78","latitude":52.10577,"longitude":21.26129,"translations":{"pt":"Otwock","it":"Otwock","ru":"Отвоцк","uk":"Отвоцьк","de":"Otwock","es":"Otwock","en":"Otwock","fr":"Otwock"}},{"country":"PL","name":"Острув-мазовецка","admin1Code":"PL.78","latitude":52.80245,"longitude":21.89507,"translations":{"pt":"Ostruv-mazovetska","it":"Ostruv-mazovetska","ru":"Острув-мазовецка","uk":"Острув-мазовецька","de":"Ostruv-mazovetska","es":"Ostruv-mazovetska","en":"Ostruv-mazovetska","fr":"Ostruv-mazovetska"}},{"country":"PL","name":"Ostrowiec świętokrzyski","admin1Code":"PL.84","latitude":50.92936,"longitude":21.38525,"translations":{"pt":"Ostrowiec świętokrzyski","it":"Ostrowiec świętokrzyski","ru":"Островец-свентокшиский","uk":"Островець-свентокшиський","de":"Ostrowiec świętokrzyski","es":"Ostrowiec świętokrzyski","en":"Ostrowiec świętokrzyski","fr":"Ostrowiec świętokrzyski"}},{"country":"PL","name":"Ostrołęka","admin1Code":"PL.78","latitude":53.08621,"longitude":21.57566,"translations":{"pt":"Ostrołęka","it":"Ostrołęka","ru":"Остроленка","uk":"Остроленка","de":"Ostrołęka","es":"Ostrołęka","en":"Ostrołęka","fr":"Ostrołęka"}},{"country":"PL","name":"Опочно","admin1Code":"PL.74","latitude":51.37569,"longitude":20.27827,"translations":{"pt":"Opochno","it":"Opochno","ru":"Опочно","uk":"Опочно","de":"Opochno","es":"Opochno","en":"Opochno","fr":"Opochno"}},{"country":"PL","name":"Olsztyn","admin1Code":"PL.85","latitude":53.77995,"longitude":20.49416,"translations":{"pt":"Olsztyn","it":"Olsztyn","ru":"Ольштын","uk":"Olsztyn","de":"Olsztyn","es":"Olsztyn","en":"Olsztyn","fr":"Olsztyn"}},{"country":"PL","name":"Olecko","admin1Code":"PL.85","latitude":54.03374,"longitude":22.50704,"translations":{"pt":"Olecko","it":"Olecko","ru":"Олецко","uk":"Олецько","de":"Treuburg","es":"Olecko","en":"Olecko","fr":"Olecko"}},{"country":"PL","name":"Ochota","admin1Code":"PL.78","latitude":52.22096,"longitude":20.98526,"translations":{"pt":"Ochota","it":"Ochota","ru":"Охота","uk":"Охота","de":"Ochota","es":"Ochota","en":"Ochota","fr":"Ochota"}},{"country":"PL","name":"Nowy targ","admin1Code":"PL.77","latitude":49.47783,"longitude":20.03228,"translations":{"pt":"Nowy targ","it":"Nowy targ","ru":"Новы-тарг","uk":"Новий тарг","de":"Nowy targ","es":"Nowy targ","en":"Nowy targ","fr":"Nowy targ"}},{"country":"PL","name":"Nowy sącz","admin1Code":"PL.77","latitude":49.62177,"longitude":20.69705,"translations":{"pt":"Nowy sącz","it":"Nowy sącz","ru":"Новы-сонч","uk":"Новий сонч","de":"Neusandez","es":"Nowy sącz","en":"Nowy sącz","fr":"Nowy sącz"}},{"country":"PL","name":"Новы-двур-мазовецки","admin1Code":"PL.78","latitude":52.43022,"longitude":20.71652,"translations":{"pt":"Novы-dvur-mazovetsky","it":"Novы-dvur-mazovetsky","ru":"Новы-двур-мазовецки","uk":"Новий-двір-мазовецький","de":"Novы-dvur-mazovetsky","es":"Novы-dvur-mazovetsky","en":"Novы-dvur-mazovetsky","fr":"Novы-dvur-mazovetsky"}},{"country":"PL","name":"Нисько","admin1Code":"PL.80","latitude":50.51987,"longitude":22.13968,"translations":{"pt":"Nys'ko","it":"Nys'ko","ru":"Ниско","uk":"Нисько","de":"Nys'ko","es":"Nys'ko","en":"Nys'ko","fr":"Nys'ko"}},{"country":"PL","name":"Sensburg","admin1Code":"PL.85","latitude":53.86437,"longitude":21.30507,"translations":{"pt":"Sensburg","it":"Sensburg","ru":"Мронгово","uk":"Мронгово","de":"Sensburg","es":"Sensburg","en":"Sensburg","fr":"Sensburg"}},{"country":"PL","name":"Мокотув","admin1Code":"PL.78","latitude":52.1934,"longitude":21.03487,"translations":{"pt":"Mokotuv","it":"Mokotuv","ru":"Мокотув","uk":"Мокотув","de":"Mokotuv","es":"Mokotuv","en":"Mokotuv","fr":"Mokotuv"}},{"country":"PL","name":"Mława","admin1Code":"PL.78","latitude":53.11278,"longitude":20.3841,"translations":{"pt":"Mława","it":"Mława","ru":"Млава","uk":"Млава","de":"Mława","es":"Mława","en":"Mława","fr":"Mława"}},{"country":"PL","name":"Mińsk mazowiecki","admin1Code":"PL.78","latitude":52.17935,"longitude":21.57251,"translations":{"pt":"Mińsk mazowiecki","it":"Mińsk mazowiecki","ru":"Миньск-мазовецкий","uk":"Мінськ-мазовецький","de":"Mińsk mazowiecki","es":"Mińsk mazowiecki","en":"Mińsk mazowiecki","fr":"Mińsk mazowiecki"}},{"country":"PL","name":"Milanówek","admin1Code":"PL.78","latitude":52.11879,"longitude":20.67155,"translations":{"pt":"Milanówek","it":"Milanówek","ru":"Милянувек","uk":"Мілянувек","de":"Milanówek","es":"Milanówek","en":"Milanówek","fr":"Milanówek"}},{"country":"PL","name":"Mielec","admin1Code":"PL.80","latitude":50.28709,"longitude":21.4239,"translations":{"pt":"Mielec","it":"Mielec","ru":"Мелец","uk":"Мелець","de":"Mielec","es":"Mielec","en":"Mielec","fr":"Mielec"}},{"country":"PL","name":"Międzyrzec podlaski","admin1Code":"PL.75","latitude":51.9864,"longitude":22.78248,"translations":{"pt":"Międzyrzec podlaski","it":"Międzyrzec podlaski","ru":"Мендзыжец-подляски","uk":"Межиріччя","de":"Międzyrzec podlaski","es":"Międzyrzec podlaski","en":"Międzyrzec podlaski","fr":"Międzyrzec podlaski"}},{"country":"PL","name":"Marki","admin1Code":"PL.78","latitude":52.32065,"longitude":21.10474,"translations":{"pt":"Marki","it":"Marki","ru":"Марки","uk":"Маркі","de":"Marki","es":"Marki","en":"Marki","fr":"Marki"}},{"country":"PL","name":"Лукув","admin1Code":"PL.75","latitude":51.929,"longitude":22.37956,"translations":{"pt":"Lukuv","it":"Lukuv","ru":"Лукув","uk":"Луків","de":"Lukuv","es":"Lukuv","en":"Lukuv","fr":"Lukuv"}},{"country":"PL","name":"Lublin","admin1Code":"PL.75","latitude":51.25,"longitude":22.56667,"translations":{"pt":"Lublin","it":"Lublino","ru":"Люблин","uk":"Люблін","de":"Lublin","es":"Lublin","en":"Lublin","fr":"Lublin"}},{"country":"PL","name":"Любартів","admin1Code":"PL.75","latitude":51.46026,"longitude":22.60952,"translations":{"pt":"Ljubartiv","it":"Ljubartiv","ru":"Любартув","uk":"Любартів","de":"Ljubartiv","es":"Ljubartiv","en":"Ljubartiv","fr":"Ljubartiv"}},{"country":"PL","name":"Łomża","admin1Code":"PL.81","latitude":53.17806,"longitude":22.05935,"translations":{"pt":"Łomża","it":"Łomża","ru":"Ломжа","uk":"Ломжа","de":"Łomża","es":"Łomża","en":"Łomża","fr":"Łomża"}},{"country":"PL","name":"Ломянкі","admin1Code":"PL.78","latitude":52.33413,"longitude":20.88602,"translations":{"pt":"Lomjanki","it":"Lomjanki","ru":"Ломянки","uk":"Ломянкі","de":"Lomjanki","es":"Lomjanki","en":"Lomjanki","fr":"Lomjanki"}},{"country":"PL","name":"Lidzbark warmiński","admin1Code":"PL.85","latitude":54.12588,"longitude":20.57954,"translations":{"pt":"Lidzbark warmiński","it":"Lidzbark warmiński","ru":"Лидзбарк-варминьски","uk":"Лідзбарк-вармінський","de":"Heilsberg","es":"Lidzbark warmiński","en":"Lidzbark warmiński","fr":"Lidzbark warmiński"}},{"country":"PL","name":"Legionowo","admin1Code":"PL.78","latitude":52.40149,"longitude":20.92664,"translations":{"pt":"Legionowo","it":"Legionowo","ru":"Легьоново","uk":"Леґьоново","de":"Legionowo","es":"Legionowo","en":"Legionowo","fr":"Legionowo"}},{"country":"PL","name":"Ленчна","admin1Code":"PL.75","latitude":51.30121,"longitude":22.88135,"translations":{"pt":"Lenchna","it":"Lenchna","ru":"Ленчна","uk":"Ленчна","de":"Lenchna","es":"Lenchna","en":"Lenchna","fr":"Lenchna"}},{"country":"PL","name":"Łapy","admin1Code":"PL.81","latitude":52.9911,"longitude":22.88422,"translations":{"pt":"Łapy","it":"Łapy","ru":"Лапы","uk":"Лапи","de":"Łapy","es":"Łapy","en":"Łapy","fr":"Łapy"}},{"country":"PL","name":"Ланьцут","admin1Code":"PL.80","latitude":50.06871,"longitude":22.22912,"translations":{"pt":"Lan'tsut","it":"Lan'tsut","ru":"Ланьцут","uk":"Ланьцут","de":"Landshut","es":"Lan'tsut","en":"Lan'tsut","fr":"Lan'tsut"}},{"country":"PL","name":"Кросно","admin1Code":"PL.80","latitude":49.68866,"longitude":21.77058,"translations":{"pt":"Krosno","it":"Krosno","ru":"Кросно","uk":"Коросно","de":"Krosno","es":"Krosno","en":"Krosno","fr":"Krosno"}},{"country":"PL","name":"Красностав","admin1Code":"PL.75","latitude":50.98464,"longitude":23.1742,"translations":{"pt":"Krasnostav","it":"Krasnostav","ru":"Красныстав","uk":"Красностав","de":"Krasnostav","es":"Krasnostav","en":"Krasnostav","fr":"Krasnostav"}},{"country":"PL","name":"Красник","admin1Code":"PL.75","latitude":50.9236,"longitude":22.22706,"translations":{"pt":"Krasnyk","it":"Krasnyk","ru":"Красник","uk":"Красник","de":"Krasnyk","es":"Krasnyk","en":"Krasnyk","fr":"Krasnyk"}},{"country":"PL","name":"Козеніце","admin1Code":"PL.78","latitude":51.58294,"longitude":21.54779,"translations":{"pt":"Kozenitse","it":"Kozenitse","ru":"Козенице","uk":"Козеніце","de":"Koschnitz","es":"Kozenitse","en":"Kozenitse","fr":"Kozenitse"}},{"country":"PL","name":"Konstancin-jeziorna","admin1Code":"PL.78","latitude":52.0938,"longitude":21.11761,"translations":{"pt":"Konstancin-jeziorna","it":"Konstancin-jeziorna","ru":"Констанцин-езерна","uk":"Констанцин-єзьорна","de":"Konstancin-jeziorna","es":"Konstancin-jeziorna","en":"Konstancin-jeziorna","fr":"Konstancin-jeziorna"}},{"country":"PL","name":"Gmina końskie","admin1Code":"PL.84","latitude":51.19166,"longitude":20.40607,"translations":{"pt":"Comuna de końskie","it":"Gmina końskie","ru":"Коньске","uk":"Ґміна конське","de":"Gmina końskie","es":"Gmina końskie","en":"Gmina końskie","fr":"Gmina końskie"}},{"country":"PL","name":"Кобилка","admin1Code":"PL.78","latitude":52.33953,"longitude":21.19589,"translations":{"pt":"Kobylka","it":"Kobylka","ru":"Кобылка","uk":"Кобилка","de":"Kobylka","es":"Kobylka","en":"Kobylka","fr":"Kobylka"}},{"country":"PL","name":"Kielce","admin1Code":"PL.84","latitude":50.87033,"longitude":20.62752,"translations":{"pt":"Kielce","it":"Kielce","ru":"Кельце","uk":"Кельце","de":"Kielce","es":"Kielce","en":"Kielce","fr":"Kielce"}},{"country":"PL","name":"Kętrzyn","admin1Code":"PL.85","latitude":54.07676,"longitude":21.37527,"translations":{"pt":"Kętrzyn","it":"Kętrzyn","ru":"Кентшин","uk":"Кентшин","de":"Rastenburg","es":"Kętrzyn","en":"Kętrzyn","fr":"Kętrzyn"}},{"country":"PL","name":"Kabaty","admin1Code":"PL.78","latitude":52.13012,"longitude":21.08148,"translations":{"pt":"Kabaty","it":"Kabaty","ru":"Kabaty","uk":"Kabaty","de":"Kabaty","es":"Kabaty","en":"Kabaty","fr":"Kabaty"}},{"country":"PL","name":"Юзефув","admin1Code":"PL.78","latitude":52.13707,"longitude":21.23589,"translations":{"pt":"Juzefuv","it":"Juzefuv","ru":"Юзефув","uk":"Юзефув","de":"Juzefuv","es":"Juzefuv","en":"Juzefuv","fr":"Juzefuv"}},{"country":"PL","name":"Gmina jędrzejów","admin1Code":"PL.84","latitude":50.63945,"longitude":20.30454,"translations":{"pt":"Comuna de jędrzejów","it":"Gmina jędrzejów","ru":"Енджеюв","uk":"Гміна єнджеюв","de":"Gmina jędrzejów","es":"Gmina jędrzejów","en":"Gmina jędrzejów","fr":"Gmina jędrzejów"}},{"country":"PL","name":"Ясло","admin1Code":"PL.80","latitude":49.74506,"longitude":21.47252,"translations":{"pt":"Jaslo","it":"Jaslo","ru":"Ясло","uk":"Ясло","de":"Jaslo","es":"Jaslo","en":"Jaslo","fr":"Jaslo"}},{"country":"PL","name":"Jarosław","admin1Code":"PL.80","latitude":50.01623,"longitude":22.67776,"translations":{"pt":"Jarosław","it":"Jarosław","ru":"Ярослав","uk":"Ярослав","de":"Jaroslau","es":"Jarosław","en":"Jarosław","fr":"Jarosław"}},{"country":"PL","name":"Hrubieszów","admin1Code":"PL.75","latitude":50.80502,"longitude":23.89251,"translations":{"pt":"Hrubieszów","it":"Hrubieszów","ru":"Хрубешув","uk":"Грубешів","de":"Hrubieszów","es":"Hrubieszów","en":"Hrubieszów","fr":"Hrubieszów"}},{"country":"PL","name":"Hajnówka","admin1Code":"PL.81","latitude":52.74328,"longitude":23.58122,"translations":{"pt":"Hajnówka","it":"Hajnówka","ru":"Хайнувка","uk":"Гайнівка","de":"Hajnówka","es":"Hajnówka","en":"Hajnówka","fr":"Hajnówka"}},{"country":"PL","name":"Grodzisk mazowiecki","admin1Code":"PL.78","latitude":52.10387,"longitude":20.6337,"translations":{"pt":"Grodzisk mazowiecki","it":"Grodzisk mazowiecki","ru":"Гродзиск-мазовецки","uk":"Гродзиськ-мазовецький","de":"Grodzisk mazowiecki","es":"Grodzisk mazowiecki","en":"Grodzisk mazowiecki","fr":"Grodzisk mazowiecki"}},{"country":"PL","name":"Граево","admin1Code":"PL.81","latitude":53.64728,"longitude":22.45537,"translations":{"pt":"Hraevo","it":"Hraevo","ru":"Граево","uk":"Граєво","de":"Hraevo","es":"Hraevo","en":"Hraevo","fr":"Hraevo"}},{"country":"PL","name":"Gorlice","admin1Code":"PL.77","latitude":49.65563,"longitude":21.16035,"translations":{"pt":"Gorlice","it":"Gorlice","ru":"Горлице","uk":"Горлиці","de":"Gorlice","es":"Gorlice","en":"Gorlice","fr":"Gorlice"}},{"country":"PL","name":"Giżycko","admin1Code":"PL.85","latitude":54.03811,"longitude":21.76441,"translations":{"pt":"Giżycko","it":"Giżycko","ru":"Гижицко","uk":"Гіжицько","de":"Lötzen","es":"Giżycko","en":"Giżycko","fr":"Giżycko"}},{"country":"PL","name":"Gierłoż","admin1Code":"PL.85","latitude":54.08134,"longitude":21.49551,"translations":{"pt":"Gierłoż","it":"Gierłoż","ru":"Gierłoż","uk":"Gierłoż","de":"Gierłoż","es":"Gierłoż","en":"Gierłoż","fr":"Gierłoż"}},{"country":"PL","name":"Гарволін","admin1Code":"PL.78","latitude":51.89747,"longitude":21.61466,"translations":{"pt":"Harvolin","it":"Harvolin","ru":"Гарволин","uk":"Гарволін","de":"Harvolin","es":"Harvolin","en":"Harvolin","fr":"Harvolin"}},{"country":"PL","name":"Ełk","admin1Code":"PL.85","latitude":53.82824,"longitude":22.36469,"translations":{"pt":"Ełk","it":"Elk","ru":"Элк","uk":"Елк","de":"Lyck","es":"Ełk","en":"Ełk","fr":"Ełk"}},{"country":"PL","name":"Działdowo","admin1Code":"PL.85","latitude":53.23958,"longitude":20.17004,"translations":{"pt":"Działdowo","it":"Działdowo","ru":"Дзялдово","uk":"Дзялдово","de":"Działdowo","es":"Działdowo","en":"Działdowo","fr":"Działdowo"}},{"country":"PL","name":"Демблін","admin1Code":"PL.75","latitude":51.55912,"longitude":21.84829,"translations":{"pt":"Demblin","it":"Demblin","ru":"Демблин","uk":"Демблін","de":"Demblin","es":"Demblin","en":"Demblin","fr":"Demblin"}},{"country":"PL","name":"Дембиця","admin1Code":"PL.80","latitude":50.05146,"longitude":21.41141,"translations":{"pt":"Dembytsja","it":"Dembytsja","ru":"Дембица","uk":"Дембиця","de":"Dembytsja","es":"Dembytsja","en":"Dembytsja","fr":"Dembytsja"}},{"country":"PL","name":"Ciechanów","admin1Code":"PL.78","latitude":52.88141,"longitude":20.61996,"translations":{"pt":"Ciechanów","it":"Ciechanów","ru":"Цеханув","uk":"Цеханув","de":"Ciechanów","es":"Ciechanów","en":"Ciechanów","fr":"Ciechanów"}},{"country":"PL","name":"Chełm","admin1Code":"PL.75","latitude":51.14312,"longitude":23.4716,"translations":{"pt":"Chełm","it":"Chełm","ru":"Хелм","uk":"Холм","de":"Chełm","es":"Chełm","en":"Chełm","fr":"Chełm"}},{"country":"PL","name":"Busko-zdrój","admin1Code":"PL.84","latitude":50.47078,"longitude":20.71884,"translations":{"pt":"Busko-zdrój","it":"Busko-zdroj","ru":"Буско-здруй","uk":"Бусько-здруй","de":"Busko-zdrój","es":"Busko-zdrój","en":"Busko-zdrój","fr":"Busko-zdrój"}},{"country":"PL","name":"Бжеско","admin1Code":"PL.77","latitude":49.96911,"longitude":20.60606,"translations":{"pt":"Bzhesko","it":"Bzhesko","ru":"Бжеско","uk":"Бжеско","de":"Bzhesko","es":"Bzhesko","en":"Bzhesko","fr":"Bzhesko"}},{"country":"PL","name":"Bochnia","admin1Code":"PL.77","latitude":49.96905,"longitude":20.43028,"translations":{"pt":"Bochnia","it":"Bochnia","ru":"Бохня","uk":"Бохня","de":"Bochnia","es":"Bochnia","en":"Bochnia","fr":"Bochnia"}},{"country":"PL","name":"Biłgoraj","admin1Code":"PL.75","latitude":50.54114,"longitude":22.72204,"translations":{"pt":"Biłgoraj","it":"Biłgoraj","ru":"Билгорай","uk":"Білґорай","de":"Biłgoraj","es":"Biłgoraj","en":"Biłgoraj","fr":"Biłgoraj"}},{"country":"PL","name":"Bieńczyce","admin1Code":"PL.77","latitude":50.08809,"longitude":20.02786,"translations":{"pt":"Bieńczyce","it":"Bieńczyce","ru":"Bieńczyce","uk":"Bieńczyce","de":"Bieńczyce","es":"Bieńczyce","en":"Bieńczyce","fr":"Bieńczyce"}},{"country":"PL","name":"Bielsk podlaski","admin1Code":"PL.81","latitude":52.76512,"longitude":23.18647,"translations":{"pt":"Bielsk podlaski","it":"Bielsk podlaski","ru":"Бельск-подляски","uk":"Більськ-підляський","de":"Bielsk podlaski","es":"Bielsk podlaski","en":"Bielsk podlaski","fr":"Bielsk podlaski"}},{"country":"PL","name":"Bielany","admin1Code":"PL.78","latitude":52.29242,"longitude":20.93531,"translations":{"pt":"Bielany","it":"Bielany","ru":"Беляны","uk":"Беляни","de":"Bielany","es":"Bielany","en":"Bielany","fr":"Bielany"}},{"country":"PL","name":"Bialystok","admin1Code":"PL.81","latitude":53.13333,"longitude":23.16433,"translations":{"pt":"Białystok","it":"Białystok","ru":"Белосток","uk":"Білосток","de":"Białystok","es":"Białystok","en":"Bialystok","fr":"Białystok"}},{"country":"PL","name":"Białołeka","admin1Code":"PL.78","latitude":52.32127,"longitude":20.97204,"translations":{"pt":"Białołeka","it":"Białołeka","ru":"Białołeka","uk":"Białołeka","de":"Białołeka","es":"Białołeka","en":"Białołeka","fr":"Białołeka"}},{"country":"PL","name":"Biała podlaska","admin1Code":"PL.75","latitude":52.03238,"longitude":23.11652,"translations":{"pt":"Biała podlaska","it":"Biała podlaska","ru":"Бяла-подляска","uk":"Біла підляська","de":"Biała podlaska","es":"Biała podlaska","en":"Biała podlaska","fr":"Biała podlaska"}},{"country":"PL","name":"Бемово","admin1Code":"PL.78","latitude":52.2546,"longitude":20.90844,"translations":{"pt":"Bemovo","it":"Bemovo","ru":"Бемово","uk":"Бемово","de":"Bemovo","es":"Bemovo","en":"Bemovo","fr":"Bemovo"}},{"country":"PL","name":"Bartoszyce","admin1Code":"PL.85","latitude":54.25354,"longitude":20.80819,"translations":{"pt":"Bartoszyce","it":"Bartoszyce","ru":"Бартошице","uk":"Бартошице","de":"Bartenstein","es":"Bartoszyce","en":"Bartoszyce","fr":"Bartoszyce"}},{"country":"PL","name":"Augustów","admin1Code":"PL.81","latitude":53.84321,"longitude":22.97979,"translations":{"pt":"Augustów","it":"Augustów","ru":"Августов","uk":"Augustów","de":"Augustów","es":"Augustów","en":"Augustów","fr":"Augustów"}},{"country":"PL","name":"Żywiec","admin1Code":"PL.83","latitude":49.68529,"longitude":19.19243,"translations":{"pt":"Żywiec","it":"Żywiec","ru":"Живец","uk":"Живець","de":"Żywiec","es":"Żywiec","en":"Żywiec","fr":"Żywiec"}},{"country":"PL","name":"Żory","admin1Code":"PL.83","latitude":50.04523,"longitude":18.70062,"translations":{"pt":"Żory","it":"Żory","ru":"Жоры","uk":"Жори","de":"Sohrau","es":"Żory","en":"Żory","fr":"Żory"}},{"country":"PL","name":"Злотув","admin1Code":"PL.86","latitude":53.36346,"longitude":17.04082,"translations":{"pt":"Zlotuv","it":"Zlotuv","ru":"Злотув","uk":"Злотув","de":"Flatow","es":"Zlotuv","en":"Zlotuv","fr":"Zlotuv"}},{"country":"PL","name":"Złotoryja","admin1Code":"PL.72","latitude":51.12637,"longitude":15.91979,"translations":{"pt":"Złotoryja","it":"Złotoryja","ru":"Злоторыя","uk":"Злотория","de":"Złotoryja","es":"Złotoryja","en":"Złotoryja","fr":"Złotoryja"}},{"country":"PL","name":"Zielona góra","admin1Code":"PL.76","latitude":51.93548,"longitude":15.50643,"translations":{"pt":"Zielona góra","it":"Zielona góra","ru":"Зелёна-гура","uk":"Зелена гура","de":"Grünberg","es":"Zielona góra","en":"Zielona góra","fr":"Zielona góra"}},{"country":"PL","name":"Zgorzelec","admin1Code":"PL.72","latitude":51.14942,"longitude":15.00835,"translations":{"pt":"Zgorzelec","it":"Zgorzelec","ru":"Згожелец","uk":"Зґожелець","de":"Zgorzelec","es":"Zgorzelec","en":"Zgorzelec","fr":"Zgorzelec"}},{"country":"PL","name":"Zgierz","admin1Code":"PL.74","latitude":51.85561,"longitude":19.40623,"translations":{"pt":"Zgierz","it":"Zgierz","ru":"Згеж","uk":"Згеж","de":"Zgierz","es":"Zgierz","en":"Zgierz","fr":"Zgierz"}},{"country":"PL","name":"Здунська воля","admin1Code":"PL.74","latitude":51.59915,"longitude":18.93974,"translations":{"pt":"Zduns'ka volja","it":"Zduns'ka volja","ru":"Здуньская-воля","uk":"Здунська воля","de":"Zduns'ka volja","es":"Zduns'ka volja","en":"Zduns'ka volja","fr":"Zduns'ka volja"}},{"country":"PL","name":"Zawiercie","admin1Code":"PL.83","latitude":50.48766,"longitude":19.41679,"translations":{"pt":"Zawiercie","it":"Zawiercie","ru":"Заверце","uk":"Заверце","de":"Zawiercie","es":"Zawiercie","en":"Zawiercie","fr":"Zawiercie"}},{"country":"PL","name":"Жара","admin1Code":"PL.76","latitude":51.64205,"longitude":15.13727,"translations":{"pt":"Zhara","it":"Zhara","ru":"Жара","uk":"Жари","de":"Zhara","es":"Zhara","en":"Zhara","fr":"Zhara"}},{"country":"PL","name":"Zakopane","admin1Code":"PL.77","latitude":49.29899,"longitude":19.94885,"translations":{"pt":"Zakopane","it":"Zakopane","ru":"Закопане","uk":"Закопане","de":"Zakopane","es":"Zakopane","en":"Zakopane","fr":"Zakopane"}},{"country":"PL","name":"Żagań","admin1Code":"PL.76","latitude":51.61759,"longitude":15.31486,"translations":{"pt":"Żagań","it":"Żagań","ru":"Жагань","uk":"Жагань","de":"Sagan","es":"Żagań","en":"Żagań","fr":"Żagań"}},{"country":"PL","name":"Zabrze","admin1Code":"PL.83","latitude":50.32492,"longitude":18.78576,"translations":{"pt":"Zabrze","it":"Zabrze","ru":"Забже","uk":"Забже","de":"Zabrze","es":"Zabrze","en":"Zabrze","fr":"Zabrze"}},{"country":"PL","name":"Ząbkowice śląskie","admin1Code":"PL.72","latitude":50.58969,"longitude":16.81239,"translations":{"pt":"Ząbkowice śląskie","it":"Ząbkowice śląskie","ru":"Зомбковице-слёнске","uk":"Зомбковіце-шльонське","de":"Ząbkowice śląskie","es":"Frankenstein","en":"Ząbkowice śląskie","fr":"Ząbkowice śląskie"}},{"country":"PL","name":"Wrzeszcz","admin1Code":"PL.82","latitude":54.37648,"longitude":18.60753,"translations":{"pt":"Wrzeszcz","it":"Wrzeszcz","ru":"Wrzeszcz","uk":"Wrzeszcz","de":"Wrzeszcz","es":"Wrzeszcz","en":"Wrzeszcz","fr":"Wrzeszcz"}},{"country":"PL","name":"Вжесьня","admin1Code":"PL.86","latitude":52.32512,"longitude":17.56519,"translations":{"pt":"Vzhes'nja","it":"Vzhes'nja","ru":"Вжесня","uk":"Вжесьня","de":"Vzhes'nja","es":"Vzhes'nja","en":"Vzhes'nja","fr":"Vzhes'nja"}},{"country":"PL","name":"Wroclaw","admin1Code":"PL.72","latitude":51.1,"longitude":17.03333,"translations":{"pt":"Breslávia","it":"Breslavia","ru":"Вроцлав","uk":"Вроцлав","de":"Wroclaw","es":"Breslavia","en":"Wroclaw","fr":"Vratislavie"}},{"country":"PL","name":"Wodzisław śląski","admin1Code":"PL.83","latitude":50.00377,"longitude":18.47205,"translations":{"pt":"Wodzisław śląski","it":"Wodzisław śląski","ru":"Водзислав-слёнски","uk":"Водзіслав-шльонський","de":"Wodzisław śląski","es":"Wodzisław śląski","en":"Wodzisław śląski","fr":"Wodzisław śląski"}},{"country":"PL","name":"Włocławek","admin1Code":"PL.73","latitude":52.64817,"longitude":19.0678,"translations":{"pt":"Włocławek","it":"Włocławek","ru":"Влоцлавек","uk":"Влоцлавек","de":"Włocławek","es":"Włocławek","en":"Włocławek","fr":"Włocławek"}},{"country":"PL","name":"Wieluń","admin1Code":"PL.74","latitude":51.22097,"longitude":18.56964,"translations":{"pt":"Wieluń","it":"Wieluń","ru":"Велюнь","uk":"Велюнь","de":"Wieluń","es":"Wieluń","en":"Wieluń","fr":"Wieluń"}},{"country":"PL","name":"Wejherowo","admin1Code":"PL.82","latitude":54.60568,"longitude":18.23559,"translations":{"pt":"Wejherowo","it":"Wejherowo","ru":"Вейхерово","uk":"Вейгерово","de":"Wejherowo","es":"Wejherowo","en":"Wejherowo","fr":"Wejherowo"}},{"country":"PL","name":"Deutsch krone","admin1Code":"PL.87","latitude":53.27787,"longitude":16.47122,"translations":{"pt":"Deutsch krone","it":"Deutsch krone","ru":"Валч","uk":"Валч","de":"Deutsch krone","es":"Deutsch krone","en":"Deutsch krone","fr":"Deutsch krone"}},{"country":"PL","name":"Wałbrzych","admin1Code":"PL.72","latitude":50.77141,"longitude":16.28432,"translations":{"pt":"Wałbrzych","it":"Wałbrzych","ru":"Валбжих","uk":"Валбжих","de":"Wałbrzych","es":"Wałbrzych","en":"Wałbrzych","fr":"Wałbrzych"}},{"country":"PL","name":"Вонгровец","admin1Code":"PL.86","latitude":52.80842,"longitude":17.19961,"translations":{"pt":"Vonhrovets","it":"Vonhrovets","ru":"Вонгровец","uk":"Вонгровець","de":"Vonhrovets","es":"Vonhrovets","en":"Vonhrovets","fr":"Vonhrovets"}},{"country":"PL","name":"Wadowice","admin1Code":"PL.77","latitude":49.88335,"longitude":19.49292,"translations":{"pt":"Wadowice","it":"Wadowice","ru":"Вадовице","uk":"Вадовіце","de":"Wadowice","es":"Wadowice","en":"Wadowice","fr":"Wadowice"}},{"country":"PL","name":"Устронь","admin1Code":"PL.83","latitude":49.72153,"longitude":18.80198,"translations":{"pt":"Ustron'","it":"Ustron'","ru":"Устронь","uk":"Устронь","de":"Ustron'","es":"Ustron'","en":"Ustron'","fr":"Ustron'"}},{"country":"PL","name":"Ustka","admin1Code":"PL.82","latitude":54.58048,"longitude":16.86194,"translations":{"pt":"Ustka","it":"Ustka","ru":"Устка","uk":"Устка","de":"Stolpmünde","es":"Ustka","en":"Ustka","fr":"Ustka"}},{"country":"PL","name":"Tychy","admin1Code":"PL.83","latitude":50.13717,"longitude":18.96641,"translations":{"pt":"Tychy","it":"Tychy","ru":"Тыхы","uk":"Тихи","de":"Tychy","es":"Tychy","en":"Tychy","fr":"Tychy"}},{"country":"PL","name":"Turek","admin1Code":"PL.86","latitude":52.01548,"longitude":18.50055,"translations":{"pt":"Turek","it":"Turek","ru":"Турек","uk":"Turek","de":"Turek","es":"Turek","en":"Turek","fr":"Turek"}},{"country":"PL","name":"Тшебіня","admin1Code":"PL.77","latitude":50.15931,"longitude":19.46966,"translations":{"pt":"Tshebinja","it":"Tshebinja","ru":"Тшебиня","uk":"Тшебіня","de":"Tshebinja","es":"Tshebinja","en":"Tshebinja","fr":"Tshebinja"}},{"country":"PL","name":"Тшцянка","admin1Code":"PL.86","latitude":53.04063,"longitude":16.45629,"translations":{"pt":"Tshtsjanka","it":"Tshtsjanka","ru":"Тшчанка","uk":"Тшцянка","de":"Tshtsjanka","es":"Tshtsjanka","en":"Tshtsjanka","fr":"Tshtsjanka"}},{"country":"PL","name":"Torun","admin1Code":"PL.73","latitude":53.01375,"longitude":18.59814,"translations":{"pt":"Torun","it":"Toruń","ru":"Торунь","uk":"Торунь","de":"Thorn","es":"Toruń","en":"Torun","fr":"Toruń"}},{"country":"PL","name":"Tczew","admin1Code":"PL.82","latitude":54.09242,"longitude":18.77787,"translations":{"pt":"Tczew","it":"Tczew","ru":"Тчев","uk":"Tczew","de":"Tczew","es":"Tczew","en":"Tczew","fr":"Tczew"}},{"country":"PL","name":"Tarnowitz","admin1Code":"PL.83","latitude":50.44548,"longitude":18.86147,"translations":{"pt":"Tarnowitz","it":"Tarnowitz","ru":"Тарновске-гуры","uk":"Тарновські гури","de":"Tarnowitz","es":"Tarnowitz","en":"Tarnowitz","fr":"Tarnowitz"}},{"country":"PL","name":"Neustettin","admin1Code":"PL.87","latitude":53.70791,"longitude":16.69937,"translations":{"pt":"Neustettin","it":"Neustettin","ru":"Щецинек","uk":"Щецинек","de":"Neustettin","es":"Neustettin","en":"Neustettin","fr":"Neustettin"}},{"country":"PL","name":"Szczecin","admin1Code":"PL.87","latitude":53.42894,"longitude":14.55302,"translations":{"pt":"Estetino","it":"Stettino","ru":"Щецин","uk":"Щецин","de":"Stettin","es":"Szczecin","en":"Szczecin","fr":"Szczecin"}},{"country":"PL","name":"Szamotuły","admin1Code":"PL.86","latitude":52.61201,"longitude":16.57794,"translations":{"pt":"Szamotuły","it":"Szamotuły","ru":"Шамотулы","uk":"Шамотули","de":"Szamotuły","es":"Szamotuły","en":"Szamotuły","fr":"Szamotuły"}},{"country":"PL","name":"Świnoujście","admin1Code":"PL.87","latitude":53.91053,"longitude":14.24712,"translations":{"pt":"Świnoujście","it":"Świnoujście","ru":"Свиноуйсьце","uk":"Свіноуйсьце","de":"Świnoujście","es":"Świnoujście","en":"Świnoujście","fr":"Świnoujście"}},{"country":"PL","name":"Świętochłowice","admin1Code":"PL.83","latitude":50.29636,"longitude":18.91726,"translations":{"pt":"Świętochłowice","it":"Świętochłowice","ru":"Свентохловице","uk":"Свентохловіце","de":"Świętochłowice","es":"Świętochłowice","en":"Świętochłowice","fr":"Świętochłowice"}},{"country":"PL","name":"Gmina świebodzin","admin1Code":"PL.76","latitude":52.24751,"longitude":15.53355,"translations":{"pt":"Comuna de świebodzin","it":"Gmina świebodzin","ru":"Свебодзин","uk":"Ґміна свебодзін","de":"Gmina świebodzin","es":"Gmina świebodzin","en":"Gmina świebodzin","fr":"Gmina świebodzin"}},{"country":"PL","name":"Gmina świecie","admin1Code":"PL.73","latitude":53.40953,"longitude":18.44742,"translations":{"pt":"Comuna de świecie","it":"Gmina świecie","ru":"Свеце","uk":"Ґміна свеце","de":"Świecie","es":"Gmina świecie","en":"Gmina świecie","fr":"Świecie"}},{"country":"PL","name":"Свебодзице","admin1Code":"PL.72","latitude":50.85974,"longitude":16.31966,"translations":{"pt":"Svebodzytse","it":"Svebodzytse","ru":"Свебодзице","uk":"Свебодзіце","de":"Svebodzytse","es":"Svebodzytse","en":"Svebodzytse","fr":"Svebodzytse"}},{"country":"PL","name":"Свідвин","admin1Code":"PL.87","latitude":53.77464,"longitude":15.77671,"translations":{"pt":"Svidvyn","it":"Svidvyn","ru":"Свидвин","uk":"Свідвин","de":"Svidvyn","es":"Svidvyn","en":"Svidvyn","fr":"Svidvyn"}},{"country":"PL","name":"Swidnica","admin1Code":"PL.72","latitude":50.84378,"longitude":16.48859,"translations":{"pt":"Swidnica","it":"Swidnica","ru":"Свидница","uk":"Свідниця","de":"Schweidnitz","es":"Swidnica","en":"Swidnica","fr":"Swidnica"}},{"country":"PL","name":"Сважендз","admin1Code":"PL.86","latitude":52.41289,"longitude":17.08503,"translations":{"pt":"Svazhendz","it":"Svazhendz","ru":"Сважендз","uk":"Сважендз","de":"Svazhendz","es":"Svazhendz","en":"Svazhendz","fr":"Svazhendz"}},{"country":"PL","name":"Сулехув","admin1Code":"PL.76","latitude":52.08362,"longitude":15.62513,"translations":{"pt":"Sulekhuv","it":"Sulekhuv","ru":"Сулехув","uk":"Сулехув","de":"Sulekhuv","es":"Sulekhuv","en":"Sulekhuv","fr":"Sulekhuv"}},{"country":"PL","name":"Стшельце-опольске","admin1Code":"PL.79","latitude":50.5107,"longitude":18.30056,"translations":{"pt":"Stshel'tse-opol'ske","it":"Stshel'tse-opol'ske","ru":"Стшельце-опольске","uk":"Стшельце-опольські","de":"Stshel'tse-opol'ske","es":"Stshel'tse-opol'ske","en":"Stshel'tse-opol'ske","fr":"Stshel'tse-opol'ske"}},{"country":"PL","name":"Стшеґом","admin1Code":"PL.72","latitude":50.96264,"longitude":16.35006,"translations":{"pt":"Stshegom","it":"Stshegom","ru":"Стшегом","uk":"Стшеґом","de":"Stshegom","es":"Stshegom","en":"Stshegom","fr":"Stshegom"}},{"country":"PL","name":"Starogard gdański","admin1Code":"PL.82","latitude":53.96396,"longitude":18.52638,"translations":{"pt":"Starogard gdański","it":"Starogard gdański","ru":"Старогард-гданьски","uk":"Старогард-ґданський","de":"Starogard gdański","es":"Starogard gdański","en":"Starogard gdański","fr":"Starogard gdański"}},{"country":"PL","name":"Stargard","admin1Code":"PL.87","latitude":53.33672,"longitude":15.0499,"translations":{"pt":"Stargard","it":"Stargard","ru":"Старгард","uk":"Старгард","de":"Stargard","es":"Stargard","en":"Stargard","fr":"Stargard"}},{"country":"PL","name":"Сьрода-великопольська","admin1Code":"PL.86","latitude":52.22843,"longitude":17.27617,"translations":{"pt":"S'roda-velykopol's'ka","it":"S'roda-velykopol's'ka","ru":"Сьрода-велькопольска","uk":"Сьрода-великопольська","de":"S'roda-velykopol's'ka","es":"S'roda-velykopol's'ka","en":"S'roda-velykopol's'ka","fr":"S'roda-velykopol's'ka"}},{"country":"PL","name":"Gmina śrem","admin1Code":"PL.86","latitude":52.08868,"longitude":17.01508,"translations":{"pt":"Comuna de śrem","it":"Gmina śrem","ru":"Срем","uk":"Ґміна сьрем","de":"Śrem","es":"Gmina śrem","en":"Gmina śrem","fr":"Gmina śrem"}},{"country":"PL","name":"Sosnowiec","admin1Code":"PL.83","latitude":50.28682,"longitude":19.10385,"translations":{"pt":"Sosnowiec","it":"Sosnowiec","ru":"Сосновец","uk":"Sosnowiec","de":"Sosnowiec","es":"Sosnowiec","en":"Sosnowiec","fr":"Sosnowiec"}},{"country":"PL","name":"Sopot","admin1Code":"PL.82","latitude":54.4418,"longitude":18.56003,"translations":{"pt":"Sopot","it":"Sopot","ru":"Сопот","uk":"Сопот","de":"Sopot","es":"Sopot","en":"Sopot","fr":"Sopot"}},{"country":"PL","name":"Solec kujawski","admin1Code":"PL.73","latitude":53.08371,"longitude":18.22572,"translations":{"pt":"Solec kujawski","it":"Solec kujawski","ru":"Солец-куявски","uk":"Солець-куявський","de":"Solec kujawski","es":"Solec kujawski","en":"Solec kujawski","fr":"Solec kujawski"}},{"country":"PL","name":"Słupsk","admin1Code":"PL.82","latitude":54.46405,"longitude":17.02872,"translations":{"pt":"Słupsk","it":"Słupsk","ru":"Слупск","uk":"Слупськ","de":"Stolp","es":"Słupsk","en":"Słupsk","fr":"Słupsk"}},{"country":"PL","name":"Słubice","admin1Code":"PL.76","latitude":52.35088,"longitude":14.56065,"translations":{"pt":"Słubice","it":"Słubice","ru":"Слубице","uk":"Слубіце","de":"Słubice","es":"Słubice","en":"Słubice","fr":"Słubice"}},{"country":"PL","name":"Skawina","admin1Code":"PL.77","latitude":49.97524,"longitude":19.82869,"translations":{"pt":"Skawina","it":"Skawina","ru":"Скавина","uk":"Скавіна","de":"Skawina","es":"Skawina","en":"Skawina","fr":"Skawina"}},{"country":"PL","name":"Sierpc","admin1Code":"PL.78","latitude":52.8568,"longitude":19.66913,"translations":{"pt":"Sierpc","it":"Sierpc","ru":"Серпц","uk":"Серпць","de":"Sierpc","es":"Sierpc","en":"Sierpc","fr":"Sierpc"}},{"country":"PL","name":"Sieradz","admin1Code":"PL.74","latitude":51.59584,"longitude":18.73023,"translations":{"pt":"Sieradz","it":"Sieradz","ru":"Серадз","uk":"Серадз","de":"Sieradz","es":"Sieradz","en":"Sieradz","fr":"Sieradz"}},{"country":"PL","name":"Siemianowice śląskie","admin1Code":"PL.83","latitude":50.32738,"longitude":19.02901,"translations":{"pt":"Siemianowice śląskie","it":"Siemianowice śląskie","ru":"Семяновице-слёнске","uk":"Семяновіце-шльонські","de":"Siemianowice śląskie","es":"Siemianowice śląskie","en":"Siemianowice śląskie","fr":"Siemianowice śląskie"}},{"country":"PL","name":"Rypin","admin1Code":"PL.73","latitude":53.06603,"longitude":19.40941,"translations":{"pt":"Rypin","it":"Rypin","ru":"Рыпин","uk":"Рипін","de":"Rypin","es":"Rypin","en":"Rypin","fr":"Rypin"}},{"country":"PL","name":"Rydułtowy","admin1Code":"PL.83","latitude":50.05857,"longitude":18.41703,"translations":{"pt":"Rydułtowy","it":"Rydułtowy","ru":"Рыдултовы","uk":"Ридултови","de":"Rydułtowy","es":"Rydułtowy","en":"Rydułtowy","fr":"Rydułtowy"}},{"country":"PL","name":"Rybnik","admin1Code":"PL.83","latitude":50.09713,"longitude":18.54179,"translations":{"pt":"Rybnik","it":"Rybnik","ru":"Рыбник","uk":"Рибник","de":"Rybnik","es":"Rybnik","en":"Rybnik","fr":"Rybnik"}},{"country":"PL","name":"Rumia","admin1Code":"PL.82","latitude":54.57092,"longitude":18.38802,"translations":{"pt":"Rumia","it":"Rumia","ru":"Румя","uk":"Румія","de":"Rumia","es":"Rumia","en":"Rumia","fr":"Rumia"}},{"country":"PL","name":"Ruda śląska","admin1Code":"PL.83","latitude":50.2584,"longitude":18.85632,"translations":{"pt":"Ruda śląska","it":"Ruda śląska","ru":"Руда-сленска","uk":"Руда-шльонська","de":"Ruda śląska","es":"Ruda śląska","en":"Ruda śląska","fr":"Ruda śląska"}},{"country":"PL","name":"Reda","admin1Code":"PL.82","latitude":54.60528,"longitude":18.34717,"translations":{"pt":"Reda","it":"Reda","ru":"Реда","uk":"Реда","de":"Reda","es":"Reda","en":"Reda","fr":"Reda"}},{"country":"PL","name":"Rawicz","admin1Code":"PL.86","latitude":51.60946,"longitude":16.85852,"translations":{"pt":"Rawicz","it":"Rawicz","ru":"Равич","uk":"Равич","de":"Rawicz","es":"Rawicz","en":"Rawicz","fr":"Rawicz"}},{"country":"PL","name":"Радзьонкув","admin1Code":"PL.83","latitude":50.40026,"longitude":18.90232,"translations":{"pt":"Radz'onkuv","it":"Radz'onkuv","ru":"Радзёнкув","uk":"Радзьонкув","de":"Radz'onkuv","es":"Radz'onkuv","en":"Radz'onkuv","fr":"Radz'onkuv"}},{"country":"PL","name":"Radomsko","admin1Code":"PL.74","latitude":51.06713,"longitude":19.44477,"translations":{"pt":"Radomsko","it":"Radomsko","ru":"Радомско","uk":"Радомсько","de":"Radomsko","es":"Radomsko","en":"Radomsko","fr":"Radomsko"}},{"country":"PL","name":"Radlin","admin1Code":"PL.83","latitude":50.0502,"longitude":18.47626,"translations":{"pt":"Radlin","it":"Radlin","ru":"Radlin","uk":"Radlin","de":"Radlin","es":"Radlin","en":"Radlin","fr":"Radlin"}},{"country":"PL","name":"Racibórz","admin1Code":"PL.83","latitude":50.09195,"longitude":18.21928,"translations":{"pt":"Racibórz","it":"Racibórz","ru":"Ратибор","uk":"Ратибор","de":"Ratibor","es":"Racibórz","en":"Racibórz","fr":"Racibórz"}},{"country":"PL","name":"Писковіце","admin1Code":"PL.83","latitude":50.4,"longitude":18.63333,"translations":{"pt":"Pyskovitse","it":"Pyskovitse","ru":"Пысковице","uk":"Писковіце","de":"Pyskovitse","es":"Pyskovitse","en":"Pyskovitse","fr":"Pyskovitse"}},{"country":"PL","name":"Pszczyna","admin1Code":"PL.83","latitude":49.98037,"longitude":18.95382,"translations":{"pt":"Pszczyna","it":"Pszczyna","ru":"Пщина","uk":"Пщина","de":"Pless","es":"Pszczyna","en":"Pszczyna","fr":"Pszczyna"}},{"country":"PL","name":"Прущ-ґданський","admin1Code":"PL.82","latitude":54.26217,"longitude":18.63625,"translations":{"pt":"Prushch-gdans'kyj","it":"Prushch-gdans'kyj","ru":"Прущ-гданьский","uk":"Прущ-ґданський","de":"Prushch-gdans'kyj","es":"Prushch-gdans'kyj","en":"Prushch-gdans'kyj","fr":"Prushch-gdans'kyj"}},{"country":"PL","name":"Прудник","admin1Code":"PL.79","latitude":50.32124,"longitude":17.57461,"translations":{"pt":"Prudnyk","it":"Prudnyk","ru":"Прудник","uk":"Прудник","de":"Prudnyk","es":"Prudnyk","en":"Prudnyk","fr":"Prudnyk"}},{"country":"PL","name":"Poznan","admin1Code":"PL.86","latitude":52.40692,"longitude":16.92993,"translations":{"pt":"Poznan","it":"Poznan","ru":"Познань","uk":"Познань","de":"Posen","es":"Posnania","en":"Poznan","fr":"Poznan"}},{"country":"PL","name":"Polkowice","admin1Code":"PL.72","latitude":51.50391,"longitude":16.07261,"translations":{"pt":"Polkowice","it":"Polkowice","ru":"Польковице","uk":"Польковіце","de":"Polkowice","es":"Polkowice","en":"Polkowice","fr":"Polkowice"}},{"country":"PL","name":"Police","admin1Code":"PL.87","latitude":53.55214,"longitude":14.57182,"translations":{"pt":"Police","it":"Police","ru":"Полиция","uk":"Поліце","de":"Police","es":"Police","en":"Police","fr":"Police"}},{"country":"PL","name":"Płock","admin1Code":"PL.78","latitude":52.54682,"longitude":19.70638,"translations":{"pt":"Płock","it":"Płock","ru":"Плоцк","uk":"Плоцьк","de":"Płock","es":"Płock","en":"Płock","fr":"Płock"}},{"country":"PL","name":"Плешев","admin1Code":"PL.86","latitude":51.89636,"longitude":17.78549,"translations":{"pt":"Pleshev","it":"Pleshev","ru":"Плешев","uk":"Плешев","de":"Pleshev","es":"Pleshev","en":"Pleshev","fr":"Pleshev"}},{"country":"PL","name":"Piotrkow trybunalski","admin1Code":"PL.74","latitude":51.40547,"longitude":19.70321,"translations":{"pt":"Piotrkow trybunalski","it":"Piotrkow trybunalski","ru":"Пётркув-трыбунальский","uk":"Пйотркув-трибунальський","de":"Piotrków trybunalski","es":"Piotrkow trybunalski","en":"Piotrkow trybunalski","fr":"Piotrków trybunalski"}},{"country":"PL","name":"Пилы","admin1Code":"PL.86","latitude":53.15145,"longitude":16.73782,"translations":{"pt":"Pylы","it":"Pylы","ru":"Пилы","uk":"Піла","de":"Pylы","es":"Pylы","en":"Pylы","fr":"Pylы"}},{"country":"PL","name":"Пекари-шльонські","admin1Code":"PL.83","latitude":50.38017,"longitude":18.92653,"translations":{"pt":"Pekary-shl'ons'ki","it":"Pekary-shl'ons'ki","ru":"Пекары-слёнске","uk":"Пекари-шльонські","de":"Pekary-shl'ons'ki","es":"Pekary-shl'ons'ki","en":"Pekary-shl'ons'ki","fr":"Pekary-shl'ons'ki"}},{"country":"PL","name":"Pabianice","admin1Code":"PL.74","latitude":51.66446,"longitude":19.35473,"translations":{"pt":"Pabianice","it":"Pabianice","ru":"Пабьянице","uk":"Пабяніце","de":"Pabianice","es":"Pabianice","en":"Pabianice","fr":"Pabianice"}},{"country":"PL","name":"Озоркув","admin1Code":"PL.74","latitude":51.96336,"longitude":19.29139,"translations":{"pt":"Ozorkuv","it":"Ozorkuv","ru":"Озоркув","uk":"Озоркув","de":"Ozorkuv","es":"Ozorkuv","en":"Ozorkuv","fr":"Ozorkuv"}},{"country":"PL","name":"Oświęcim","admin1Code":"PL.77","latitude":50.03437,"longitude":19.21037,"translations":{"pt":"Oświęcim","it":"Auschwitz","ru":"Освенцим","uk":"Освенцим","de":"Auschwitz","es":"Auschwitz","en":"Oświęcim","fr":"Auschwitz"}},{"country":"PL","name":"Ostrów wielkopolski","admin1Code":"PL.86","latitude":51.65501,"longitude":17.80686,"translations":{"pt":"Ostrów wielkopolski","it":"Ostrów wielkopolski","ru":"Острув-велькопольски","uk":"Острув-великопольський","de":"Ostrów wielkopolski","es":"Ostrów wielkopolski","en":"Ostrów wielkopolski","fr":"Ostrów wielkopolski"}},{"country":"PL","name":"Ostróda","admin1Code":"PL.85","latitude":53.69671,"longitude":19.96486,"translations":{"pt":"Ostróda","it":"Ostróda","ru":"Оструда","uk":"Оструда","de":"Osterode","es":"Ostróda","en":"Ostróda","fr":"Ostróda"}},{"country":"PL","name":"Espenkrug","admin1Code":"PL.82","latitude":54.43109,"longitude":18.46727,"translations":{"pt":"Espenkrug","it":"Espenkrug","ru":"Espenkrug","uk":"Espenkrug","de":"Espenkrug","es":"Espenkrug","en":"Espenkrug","fr":"Espenkrug"}},{"country":"PL","name":"Ожеше","admin1Code":"PL.83","latitude":50.15595,"longitude":18.77923,"translations":{"pt":"Ozheshe","it":"Ozheshe","ru":"Ожеше","uk":"Ожеше","de":"Ozheshe","es":"Ozheshe","en":"Ozheshe","fr":"Ozheshe"}},{"country":"PL","name":"Opole","admin1Code":"PL.79","latitude":50.67211,"longitude":17.92533,"translations":{"pt":"Opole","it":"Opole","ru":"Ополе","uk":"Ополе","de":"Oppeln","es":"Opole","en":"Opole","fr":"Opole"}},{"country":"PL","name":"Олькуш","admin1Code":"PL.77","latitude":50.2813,"longitude":19.56503,"translations":{"pt":"Ol'kush","it":"Ol'kush","ru":"Олькуш","uk":"Олькуш","de":"Ilkenau","es":"Ol'kush","en":"Ol'kush","fr":"Ol'kush"}},{"country":"PL","name":"Олесница","admin1Code":"PL.72","latitude":51.21338,"longitude":17.38986,"translations":{"pt":"Olesnytsa","it":"Olesnytsa","ru":"Олесница","uk":"Олесьниця","de":"Olesnytsa","es":"Olesnytsa","en":"Olesnytsa","fr":"Olesnytsa"}},{"country":"PL","name":"Ohlau","admin1Code":"PL.72","latitude":50.9466,"longitude":17.2926,"translations":{"pt":"Ohlau","it":"Ohlau","ru":"Олава","uk":"Олава","de":"Ohlau","es":"Ohlau","en":"Ohlau","fr":"Ohlau"}},{"country":"PL","name":"Оборники","admin1Code":"PL.86","latitude":52.64739,"longitude":16.81406,"translations":{"pt":"Obornyky","it":"Obornyky","ru":"Оборники","uk":"Оборники","de":"Obornyky","es":"Obornyky","en":"Obornyky","fr":"Obornyky"}},{"country":"PL","name":"Nysa","admin1Code":"PL.79","latitude":50.47379,"longitude":17.33437,"translations":{"pt":"Nysa","it":"Nysa","ru":"Ныса","uk":"Ниса","de":"Nysa","es":"Nysa","en":"Nysa","fr":"Nysa"}},{"country":"PL","name":"Новий томишль","admin1Code":"PL.86","latitude":52.3195,"longitude":16.12844,"translations":{"pt":"Novyj tomyshl'","it":"Novyj tomyshl'","ru":"Новы-томысль","uk":"Новий томишль","de":"Novyj tomyshl'","es":"Novyj tomyshl'","en":"Novyj tomyshl'","fr":"Novyj tomyshl'"}},{"country":"PL","name":"Новогард","admin1Code":"PL.87","latitude":53.67437,"longitude":15.1163,"translations":{"pt":"Novohard","it":"Novohard","ru":"Новогард","uk":"Новогард","de":"Novohard","es":"Novohard","en":"Novohard","fr":"Novohard"}},{"country":"PL","name":"Нова суль","admin1Code":"PL.76","latitude":51.80333,"longitude":15.71702,"translations":{"pt":"Nova sul'","it":"Nova sul'","ru":"Нова-суль","uk":"Нова суль","de":"Nova sul'","es":"Nova sul'","en":"Nova sul'","fr":"Nova sul'"}},{"country":"PL","name":"Neurode","admin1Code":"PL.72","latitude":50.58008,"longitude":16.50164,"translations":{"pt":"Neurode","it":"Neurode","ru":"Нова-руда","uk":"Нова руда","de":"Neurode","es":"Neurode","en":"Neurode","fr":"Neurode"}},{"country":"PL","name":"Намислув","admin1Code":"PL.79","latitude":51.07592,"longitude":17.72284,"translations":{"pt":"Namysluv","it":"Namysluv","ru":"Намыслув","uk":"Намислув","de":"Namysluv","es":"Namysluv","en":"Namysluv","fr":"Namysluv"}},{"country":"PL","name":"Nakło nad notecią","admin1Code":"PL.73","latitude":53.14214,"longitude":17.60181,"translations":{"pt":"Nakło nad notecią","it":"Nakło nad notecią","ru":"Накло-над-нотецён","uk":"Накло-над-нотецем","de":"Nakło nad notecią","es":"Nakło nad notecią","en":"Nakło nad notecią","fr":"Nakło nad notecią"}},{"country":"PL","name":"Мышков","admin1Code":"PL.83","latitude":50.5752,"longitude":19.32461,"translations":{"pt":"Mыshkov","it":"Mыshkov","ru":"Мышков","uk":"Мишкув","de":"Mыshkov","es":"Mыshkov","en":"Mыshkov","fr":"Mыshkov"}},{"country":"PL","name":"Mysłowice","admin1Code":"PL.83","latitude":50.20745,"longitude":19.16668,"translations":{"pt":"Mysłowice","it":"Mysłowice","ru":"Мысловице","uk":"Мисловіце","de":"Mysłowice","es":"Mysłowice","en":"Mysłowice","fr":"Mysłowice"}},{"country":"PL","name":"Мисленіце","admin1Code":"PL.77","latitude":49.83383,"longitude":19.9383,"translations":{"pt":"Myslenitse","it":"Myslenitse","ru":"Мысленице","uk":"Мисленіце","de":"Myslenitse","es":"Myslenitse","en":"Myslenitse","fr":"Myslenitse"}},{"country":"PL","name":"Mikołów","admin1Code":"PL.83","latitude":50.17103,"longitude":18.9041,"translations":{"pt":"Mikołów","it":"Mikołów","ru":"Миколув","uk":"Міколув","de":"Nikolai","es":"Mikołów","en":"Mikołów","fr":"Mikołów"}},{"country":"PL","name":"Międzyrzecz","admin1Code":"PL.76","latitude":52.44461,"longitude":15.57801,"translations":{"pt":"Międzyrzecz","it":"Międzyrzecz","ru":"Мендзыжеч","uk":"Мендзижеч","de":"Międzyrzecz","es":"Międzyrzecz","en":"Międzyrzecz","fr":"Międzyrzecz"}},{"country":"PL","name":"Malbork","admin1Code":"PL.82","latitude":54.03591,"longitude":19.0266,"translations":{"pt":"Malbork","it":"Malbork","ru":"Мальборк","uk":"Мальборк","de":"Marienburg","es":"Malbork","en":"Malbork","fr":"Malbork"}},{"country":"PL","name":"Любон","admin1Code":"PL.86","latitude":52.34705,"longitude":16.89267,"translations":{"pt":"Ljubon","it":"Ljubon","ru":"Любон","uk":"Любонь","de":"Ljubon","es":"Ljubon","en":"Ljubon","fr":"Ljubon"}},{"country":"PL","name":"Lubliniec","admin1Code":"PL.83","latitude":50.66897,"longitude":18.6844,"translations":{"pt":"Lubliniec","it":"Lubliniec","ru":"Люблинец","uk":"Люблінець","de":"Lubliniec","es":"Lubliniec","en":"Lubliniec","fr":"Lubliniec"}},{"country":"PL","name":"Lubin","admin1Code":"PL.72","latitude":51.40089,"longitude":16.20149,"translations":{"pt":"Lubin","it":"Lubin","ru":"Любин","uk":"Любін","de":"Lüben","es":"Lubin","en":"Lubin","fr":"Lubin"}},{"country":"PL","name":"Lauban","admin1Code":"PL.72","latitude":51.12014,"longitude":15.28768,"translations":{"pt":"Lauban","it":"Lauban","ru":"Любань","uk":"Любань","de":"Lauban","es":"Lauban","en":"Lauban","fr":"Lauban"}},{"country":"PL","name":"Lowicz","admin1Code":"PL.74","latitude":52.10714,"longitude":19.94525,"translations":{"pt":"Łowicz","it":"Łowicz","ru":"Лович","uk":"Лович","de":"Łowicz","es":"Lowicz","en":"Lowicz","fr":"Łowicz"}},{"country":"PL","name":"Lodz","admin1Code":"PL.74","latitude":51.77058,"longitude":19.47395,"translations":{"pt":"Łódź","it":"Łódź","ru":"Лодзь","uk":"Лодзь","de":"Łódź","es":"Lodz","en":"Lodz","fr":"Łódź"}},{"country":"PL","name":"Лібйонж","admin1Code":"PL.77","latitude":50.10396,"longitude":19.31568,"translations":{"pt":"Libjonzh","it":"Libjonzh","ru":"Либёнж","uk":"Лібйонж","de":"Libjonzh","es":"Libjonzh","en":"Libjonzh","fr":"Libjonzh"}},{"country":"PL","name":"Leszno","admin1Code":"PL.86","latitude":51.84034,"longitude":16.57494,"translations":{"pt":"Leszno","it":"Leszno","ru":"Лешно","uk":"Лешно","de":"Leszno","es":"Leszno","en":"Leszno","fr":"Leszno"}},{"country":"PL","name":"Liegnitz","admin1Code":"PL.72","latitude":51.21006,"longitude":16.1619,"translations":{"pt":"Liegnitz","it":"Liegnitz","ru":"Легница","uk":"Легниця","de":"Liegnitz","es":"Liegnitz","en":"Liegnitz","fr":"Liegnitz"}},{"country":"PL","name":"Лендзіни","admin1Code":"PL.83","latitude":50.14264,"longitude":19.13149,"translations":{"pt":"Lendziny","it":"Lendziny","ru":"Лендзины","uk":"Лендзіни","de":"Lendziny","es":"Lendziny","en":"Lendziny","fr":"Lendziny"}},{"country":"PL","name":"Łęczyca","admin1Code":"PL.74","latitude":52.05959,"longitude":19.19972,"translations":{"pt":"Łęczyca","it":"Łęczyca","ru":"Ленчица","uk":"Ленчиця","de":"Łęczyca","es":"Łęczyca","en":"Łęczyca","fr":"Łęczyca"}},{"country":"PL","name":"Лемборк","admin1Code":"PL.82","latitude":54.53921,"longitude":17.75012,"translations":{"pt":"Lembork","it":"Lembork","ru":"Лемборк","uk":"Лемборк","de":"Lembork","es":"Lembork","en":"Lembork","fr":"Lembork"}},{"country":"PL","name":"Oberlazisk","admin1Code":"PL.83","latitude":50.14952,"longitude":18.84215,"translations":{"pt":"Oberlazisk","it":"Oberlazisk","ru":"Лазиска-гурне","uk":"Лазиська-гурне","de":"Oberlazisk","es":"Oberlazisk","en":"Oberlazisk","fr":"Oberlazisk"}},{"country":"PL","name":"Ласьк","admin1Code":"PL.74","latitude":51.59056,"longitude":19.13278,"translations":{"pt":"Las'k","it":"Las'k","ru":"Ласк","uk":"Ласьк","de":"Lask","es":"Las'k","en":"Las'k","fr":"Las'k"}},{"country":"PL","name":"Kwidzyn","admin1Code":"PL.82","latitude":53.72495,"longitude":18.93114,"translations":{"pt":"Kwidzyn","it":"Kwidzyn","ru":"Квидзын","uk":"Квідзин","de":"Marienwerder","es":"Kwidzyn","en":"Kwidzyn","fr":"Kwidzyn"}},{"country":"PL","name":"Kutno","admin1Code":"PL.74","latitude":52.23064,"longitude":19.36409,"translations":{"pt":"Kutno","it":"Kutno","ru":"Кутно","uk":"Кутно","de":"Kutno","es":"Kutno","en":"Kutno","fr":"Kutno"}},{"country":"PL","name":"Кротошин","admin1Code":"PL.86","latitude":51.69868,"longitude":17.43738,"translations":{"pt":"Krotoshyn","it":"Krotoshyn","ru":"Кротошин","uk":"Кротошин","de":"Krotoshyn","es":"Krotoshyn","en":"Krotoshyn","fr":"Krotoshyn"}},{"country":"PL","name":"Крапковіце","admin1Code":"PL.79","latitude":50.47515,"longitude":17.96539,"translations":{"pt":"Krapkovitse","it":"Krapkovitse","ru":"Крапковице","uk":"Крапковіце","de":"Krapkovitse","es":"Krapkovitse","en":"Krapkovitse","fr":"Krapkovitse"}},{"country":"PL","name":"Krakow","admin1Code":"PL.77","latitude":50.06143,"longitude":19.93658,"translations":{"pt":"Cracóvia","it":"Cracovia","ru":"Краков","uk":"Краків","de":"Krakau","es":"Cracovia","en":"Krakow","fr":"Cracovie"}},{"country":"PL","name":"Koszalin","admin1Code":"PL.87","latitude":54.19438,"longitude":16.17222,"translations":{"pt":"Koszalin","it":"Koszalin","ru":"Кошалин","uk":"Кошалін","de":"Koszalin","es":"Koszalin","en":"Koszalin","fr":"Koszalin"}},{"country":"PL","name":"Cüstrin","admin1Code":"PL.76","latitude":52.58713,"longitude":14.64953,"translations":{"pt":"Cüstrin","it":"Cüstrin","ru":"Костшин-над-одрон","uk":"Костшин-над-одрою","de":"Küstrin an der oder","es":"Cüstrin","en":"Cüstrin","fr":"Cüstrin"}},{"country":"PL","name":"Косьцежина","admin1Code":"PL.82","latitude":54.12226,"longitude":17.98119,"translations":{"pt":"Kos'tsezhyna","it":"Kos'tsezhyna","ru":"Косьцежина","uk":"Косьцежина","de":"Kos'tsezhyna","es":"Kos'tsezhyna","en":"Kos'tsezhyna","fr":"Kos'tsezhyna"}},{"country":"PL","name":"Kościan","admin1Code":"PL.86","latitude":52.08829,"longitude":16.64866,"translations":{"pt":"Kościan","it":"Kościan","ru":"Косьцян","uk":"Косцян","de":"Kościan","es":"Kościan","en":"Kościan","fr":"Kościan"}},{"country":"PL","name":"Константинув-лодзький","admin1Code":"PL.74","latitude":51.74776,"longitude":19.32564,"translations":{"pt":"Konstantynuv-lodz'kyj","it":"Konstantynuv-lodz'kyj","ru":"Константынув-лодзинский","uk":"Константинув-лодзький","de":"Konstantynuv-lodz'kyj","es":"Konstantynuv-lodz'kyj","en":"Konstantynuv-lodz'kyj","fr":"Konstantynuv-lodz'kyj"}},{"country":"PL","name":"Konin","admin1Code":"PL.86","latitude":52.22338,"longitude":18.25121,"translations":{"pt":"Konin","it":"Konin","ru":"Конин","uk":"Конін","de":"Konin","es":"Konin","en":"Konin","fr":"Konin"}},{"country":"PL","name":"Kołobrzeg","admin1Code":"PL.87","latitude":54.17565,"longitude":15.58342,"translations":{"pt":"Kołobrzeg","it":"Kołobrzeg","ru":"Колобжег","uk":"Колобжег","de":"Kolberg","es":"Kołobrzeg","en":"Kołobrzeg","fr":"Kołobrzeg"}},{"country":"PL","name":"Koło","admin1Code":"PL.86","latitude":52.20024,"longitude":18.63865,"translations":{"pt":"Koło","it":"Koło","ru":"Коло","uk":"Коло","de":"Koło","es":"Koło","en":"Koło","fr":"Koło"}},{"country":"PL","name":"Кнурув","admin1Code":"PL.83","latitude":50.21971,"longitude":18.65067,"translations":{"pt":"Knuruv","it":"Knuruv","ru":"Кнурув","uk":"Кнурув","de":"Knuruv","es":"Knuruv","en":"Knuruv","fr":"Knuruv"}},{"country":"PL","name":"Ключборк","admin1Code":"PL.79","latitude":50.97281,"longitude":18.21816,"translations":{"pt":"Kljuchbork","it":"Kljuchbork","ru":"Ключборк","uk":"Ключборк","de":"Kljuchbork","es":"Kljuchbork","en":"Kljuchbork","fr":"Kljuchbork"}},{"country":"PL","name":"Kłodzko","admin1Code":"PL.72","latitude":50.43488,"longitude":16.66145,"translations":{"pt":"Kłodzko","it":"Kłodzko","ru":"Клодзко","uk":"Клодзько","de":"Kłodzko","es":"Kłodzko","en":"Kłodzko","fr":"Kłodzko"}},{"country":"PL","name":"Kenty","admin1Code":"PL.77","latitude":49.88214,"longitude":19.22333,"translations":{"pt":"Kenty","it":"Kenty","ru":"Кенты","uk":"Кенти","de":"Kenty","es":"Kenty","en":"Kenty","fr":"Kenty"}},{"country":"PL","name":"Кендзежин-козле","admin1Code":"PL.79","latitude":50.34984,"longitude":18.22606,"translations":{"pt":"Kendzezhyn-kozle","it":"Kendzezhyn-kozle","ru":"Кендзежин-козле","uk":"Кендзежин-козьле","de":"Kendzezhyn-kozle","es":"Kendzezhyn-kozle","en":"Kendzezhyn-kozle","fr":"Kendzezhyn-kozle"}},{"country":"PL","name":"Katowice","admin1Code":"PL.83","latitude":50.25841,"longitude":19.02754,"translations":{"pt":"Katowice","it":"Katowice","ru":"Катовице","uk":"Катовіце","de":"Kattowitz","es":"Katowice","en":"Katowice","fr":"Katowice"}},{"country":"PL","name":"Kartuzy","admin1Code":"PL.82","latitude":54.33424,"longitude":18.19735,"translations":{"pt":"Kartuzy","it":"Kartuzy","ru":"Картузы","uk":"Картузи","de":"Kartuzy","es":"Kartuzy","en":"Kartuzy","fr":"Kartuzy"}},{"country":"PL","name":"Landeshut","admin1Code":"PL.72","latitude":50.78314,"longitude":16.03037,"translations":{"pt":"Landeshut","it":"Landeshut","ru":"Каменна-гура","uk":"Каменна ґура","de":"Landeshut","es":"Landeshut","en":"Landeshut","fr":"Landeshut"}},{"country":"PL","name":"Kalisz","admin1Code":"PL.86","latitude":51.76109,"longitude":18.09102,"translations":{"pt":"Kalisz","it":"Kalisz","ru":"Калиш","uk":"Каліш","de":"Kalisch","es":"Kalisz","en":"Kalisz","fr":"Kalisz"}},{"country":"PL","name":"Jelenia góra","admin1Code":"PL.72","latitude":50.89973,"longitude":15.72899,"translations":{"pt":"Jelenia góra","it":"Jelenia góra","ru":"Jelenia góra","uk":"Jelenia góra","de":"Jelenia góra","es":"Jelenia góra","en":"Jelenia góra","fr":"Jelenia góra"}},{"country":"PL","name":"Zakłady samochodowe jelcz sa","admin1Code":"PL.72","latitude":51.02102,"longitude":17.32095,"translations":{"pt":"Zakłady samochodowe jelcz sa","it":"Zakłady samochodowe jelcz sa","ru":"Zakłady samochodowe jelcz sa","uk":"Zakłady samochodowe jelcz sa","de":"Zakłady samochodowe jelcz sa","es":"Zakłady samochodowe jelcz sa","en":"Zakłady samochodowe jelcz sa","fr":"Zakłady samochodowe jelcz sa"}},{"country":"PL","name":"Jaworzno","admin1Code":"PL.83","latitude":50.20528,"longitude":19.27498,"translations":{"pt":"Jaworzno","it":"Jaworzno","ru":"Явожно","uk":"Явожно","de":"Jaworzno","es":"Jaworzno","en":"Jaworzno","fr":"Jaworzno"}},{"country":"PL","name":"Jauer","admin1Code":"PL.72","latitude":51.05132,"longitude":16.19347,"translations":{"pt":"Jauer","it":"Jauer","ru":"Явор","uk":"Явор","de":"Jauer","es":"Jauer","en":"Jauer","fr":"Jauer"}},{"country":"PL","name":"Jastrzębie zdrój","admin1Code":"PL.83","latitude":49.95542,"longitude":18.57479,"translations":{"pt":"Jastrzębie zdrój","it":"Jastrzębie zdrój","ru":"Ястшембе-здруй","uk":"Jastrzębie zdrój","de":"Jastrzębie zdrój","es":"Jastrzębie-zdrój","en":"Jastrzębie zdrój","fr":"Jastrzębie zdrój"}},{"country":"PL","name":"Jarocin","admin1Code":"PL.86","latitude":51.97266,"longitude":17.50256,"translations":{"pt":"Jarocin","it":"Jarocin","ru":"Яроцин","uk":"Яроцин","de":"Jarocin","es":"Jarocin","en":"Jarocin","fr":"Jarocin"}},{"country":"PL","name":"Inowrocław","admin1Code":"PL.73","latitude":52.79886,"longitude":18.26387,"translations":{"pt":"Inowrocław","it":"Inowrocław","ru":"Иновроцлав","uk":"Іновроцлав","de":"Inowrocław","es":"Inowrocław","en":"Inowrocław","fr":"Inowrocław"}},{"country":"PL","name":"Iława","admin1Code":"PL.85","latitude":53.59601,"longitude":19.56849,"translations":{"pt":"Iława","it":"Iława","ru":"Илава","uk":"Ілава","de":"Deutsch eylau","es":"Iława","en":"Iława","fr":"Iława"}},{"country":"PL","name":"Gubin","admin1Code":"PL.76","latitude":51.94956,"longitude":14.72837,"translations":{"pt":"Gubin","it":"Gubin","ru":"Губин","uk":"Ґубін","de":"Guben","es":"Gubin","en":"Gubin","fr":"Gubin"}},{"country":"PL","name":"Grzegórzki","admin1Code":"PL.77","latitude":50.06423,"longitude":19.96761,"translations":{"pt":"Grzegórzki","it":"Grzegórzki","ru":"Grzegórzki","uk":"Grzegórzki","de":"Grzegórzki","es":"Grzegórzki","en":"Grzegórzki","fr":"Grzegórzki"}},{"country":"PL","name":"Gryfino","admin1Code":"PL.87","latitude":53.25243,"longitude":14.48831,"translations":{"pt":"Gryfino","it":"Gryfino","ru":"Грыфино","uk":"Грифіно","de":"Gryfino","es":"Gryfino","en":"Gryfino","fr":"Gryfino"}},{"country":"PL","name":"Greifenberg","admin1Code":"PL.87","latitude":53.9165,"longitude":15.20027,"translations":{"pt":"Greifenberg","it":"Greifenberg","ru":"Грыфице","uk":"Грифіце","de":"Gryfice","es":"Greifenberg","en":"Greifenberg","fr":"Greifenberg"}},{"country":"PL","name":"Grudziądz","admin1Code":"PL.73","latitude":53.48411,"longitude":18.75366,"translations":{"pt":"Grudziądz","it":"Grudziądz","ru":"Грудзендз","uk":"Грудзьондз","de":"Graudenz","es":"Grudziądz","en":"Grudziądz","fr":"Grudziądz"}},{"country":"PL","name":"Gostynin","admin1Code":"PL.78","latitude":52.42938,"longitude":19.46194,"translations":{"pt":"Gostynin","it":"Gostynin","ru":"Гостынин","uk":"Гостинін","de":"Gostynin","es":"Gostynin","en":"Gostynin","fr":"Gostynin"}},{"country":"PL","name":"Гостын","admin1Code":"PL.86","latitude":51.88247,"longitude":17.01225,"translations":{"pt":"Hostыn","it":"Hostыn","ru":"Гостын","uk":"Гостинь","de":"Hostыn","es":"Hostыn","en":"Hostыn","fr":"Hostыn"}},{"country":"PL","name":"Gorzów wielkopolski","admin1Code":"PL.76","latitude":52.73679,"longitude":15.22878,"translations":{"pt":"Gorzów wielkopolski","it":"Gorzów wielkopolski","ru":"Гожув-велькопольски","uk":"Ґожув-велькопольський","de":"Gorzów wielkopolski","es":"Gorzów wielkopolski","en":"Gorzów wielkopolski","fr":"Gorzów wielkopolski"}},{"country":"PL","name":"Goleniów","admin1Code":"PL.87","latitude":53.56392,"longitude":14.82854,"translations":{"pt":"Goleniów","it":"Goleniów","ru":"Голенюв","uk":"Голенюв","de":"Goleniów","es":"Goleniów","en":"Goleniów","fr":"Goleniów"}},{"country":"PL","name":"Gniezno","admin1Code":"PL.86","latitude":52.53481,"longitude":17.58259,"translations":{"pt":"Gniezno","it":"Gniezno","ru":"Гнезно","uk":"Гнезно","de":"Gniezno","es":"Gniezno","en":"Gniezno","fr":"Gniezno"}},{"country":"PL","name":"Ґлухолази","admin1Code":"PL.79","latitude":50.31505,"longitude":17.38355,"translations":{"pt":"Glukholazy","it":"Glukholazy","ru":"Глухолазы","uk":"Ґлухолази","de":"Glukholazy","es":"Glukholazy","en":"Glukholazy","fr":"Glukholazy"}},{"country":"PL","name":"Гловно","admin1Code":"PL.74","latitude":51.96463,"longitude":19.71565,"translations":{"pt":"Hlovno","it":"Hlovno","ru":"Гловно","uk":"Гловно","de":"Hlovno","es":"Hlovno","en":"Hlovno","fr":"Hlovno"}},{"country":"PL","name":"Głogów","admin1Code":"PL.72","latitude":51.66361,"longitude":16.0845,"translations":{"pt":"Głogów","it":"Głogów","ru":"Глогув","uk":"Ґлоґув","de":"Głogów","es":"Glogovia","en":"Głogów","fr":"Głogów"}},{"country":"PL","name":"Gliwice","admin1Code":"PL.83","latitude":50.29761,"longitude":18.67658,"translations":{"pt":"Gliwice","it":"Gliwice","ru":"Гливице","uk":"Глівіце","de":"Gleiwitz","es":"Gliwice","en":"Gliwice","fr":"Gliwice"}},{"country":"PL","name":"Gdynia","admin1Code":"PL.82","latitude":54.51889,"longitude":18.53188,"translations":{"pt":"Gdynia","it":"Gdynia","ru":"Гдыня","uk":"Гдиня","de":"Gdingen","es":"Gdynia","en":"Gdynia","fr":"Gdynia"}},{"country":"PL","name":"Gdansk","admin1Code":"PL.82","latitude":54.35227,"longitude":18.64912,"translations":{"pt":"Gdańsk","it":"Danzica","ru":"Гданьск","uk":"Гданськ","de":"Danzig","es":"Gdansk","en":"Gdansk","fr":"Gdańsk"}},{"country":"PL","name":"Striesau","admin1Code":"PL.73","latitude":53.14821,"longitude":18.17036,"translations":{"pt":"Striesau","it":"Striesau","ru":"Striesau","uk":"Striesau","de":"Striesau","es":"Striesau","en":"Striesau","fr":"Striesau"}},{"country":"PL","name":"Elblag","admin1Code":"PL.85","latitude":54.1522,"longitude":19.40884,"translations":{"pt":"Elblag","it":"Elbląg","ru":"Эльблонг","uk":"Ельблонг","de":"Elbing","es":"Elbląg","en":"Elblag","fr":"Elbląg"}},{"country":"PL","name":"Reichenbach","admin1Code":"PL.72","latitude":50.7282,"longitude":16.65141,"translations":{"pt":"Reichenbach","it":"Reichenbach","ru":"Дзержонюв","uk":"Дзержонюв","de":"Reichenbach im eulengebirge","es":"Reichenbach","en":"Reichenbach","fr":"Reichenbach"}},{"country":"PL","name":"Dąbrowa górnicza","admin1Code":"PL.83","latitude":50.33394,"longitude":19.20479,"translations":{"pt":"Dąbrowa górnicza","it":"Dąbrowa górnicza","ru":"Домброва-гурнича","uk":"Домброва-гурнича","de":"Dąbrowa górnicza","es":"Dąbrowa górnicza","en":"Dąbrowa górnicza","fr":"Dąbrowa górnicza"}},{"country":"PL","name":"Częstochowa","admin1Code":"PL.83","latitude":50.79646,"longitude":19.12409,"translations":{"pt":"Częstochowa","it":"Częstochowa","ru":"Ченстохова","uk":"Ченстохова","de":"Czenstochau","es":"Częstochowa","en":"Częstochowa","fr":"Częstochowa"}},{"country":"PL","name":"Червйонка-лещини","admin1Code":"PL.83","latitude":50.15007,"longitude":18.67762,"translations":{"pt":"Chervjonka-leshchyny","it":"Chervjonka-leshchyny","ru":"Червёнка-лещины","uk":"Червйонка-лещини","de":"Chervjonka-leshchyny","es":"Chervjonka-leshchyny","en":"Chervjonka-leshchyny","fr":"Chervjonka-leshchyny"}},{"country":"PL","name":"Czeladź","admin1Code":"PL.83","latitude":50.31542,"longitude":19.07824,"translations":{"pt":"Czeladź","it":"Czeladź","ru":"Czeladź","uk":"Czeladź","de":"Czeladź","es":"Czeladź","en":"Czeladź","fr":"Czeladź"}},{"country":"PL","name":"Чеховіце-дзедзіце","admin1Code":"PL.83","latitude":49.91342,"longitude":19.00479,"translations":{"pt":"Chekhovitse-dzedzitse","it":"Chekhovitse-dzedzitse","ru":"Чеховице-дзедзице","uk":"Чеховіце-дзедзіце","de":"Chekhovitse-dzedzitse","es":"Chekhovitse-dzedzitse","en":"Chekhovitse-dzedzitse","fr":"Chekhovitse-dzedzitse"}},{"country":"PL","name":"Cieszyn","admin1Code":"PL.83","latitude":49.75133,"longitude":18.63213,"translations":{"pt":"Cieszyn","it":"Cieszyn","ru":"Цешин","uk":"Цешин","de":"Teschen","es":"Cieszyn","en":"Cieszyn","fr":"Cieszyn"}},{"country":"PL","name":"Chrzanów","admin1Code":"PL.77","latitude":50.13546,"longitude":19.40203,"translations":{"pt":"Chrzanów","it":"Chrzanów","ru":"Хшанув","uk":"Хшанув","de":"Chrzanów","es":"Chrzanów","en":"Chrzanów","fr":"Chrzanów"}},{"country":"PL","name":"Хощно","admin1Code":"PL.87","latitude":53.16905,"longitude":15.42054,"translations":{"pt":"Khoshchno","it":"Khoshchno","ru":"Хощно","uk":"Хощно","de":"Khoshchno","es":"Khoshchno","en":"Khoshchno","fr":"Khoshchno"}},{"country":"PL","name":"Chorzów","admin1Code":"PL.83","latitude":50.30582,"longitude":18.9742,"translations":{"pt":"Chorzów","it":"Chorzów","ru":"Хожув","uk":"Хожув","de":"Chorzów","es":"Chorzów","en":"Chorzów","fr":"Chorzów"}},{"country":"PL","name":"Chojnice","admin1Code":"PL.82","latitude":53.69554,"longitude":17.55701,"translations":{"pt":"Chojnice","it":"Chojnice","ru":"Хойнице","uk":"Хойніце","de":"Konitz","es":"Chojnice","en":"Chojnice","fr":"Chojnice"}},{"country":"PL","name":"Chodzież","admin1Code":"PL.86","latitude":52.99505,"longitude":16.9198,"translations":{"pt":"Chodzież","it":"Chodzież","ru":"Ходзеж","uk":"Ходзеж","de":"Chodzież","es":"Chodzież","en":"Chodzież","fr":"Chodzież"}},{"country":"PL","name":"Chełmża","admin1Code":"PL.73","latitude":53.18463,"longitude":18.60466,"translations":{"pt":"Chełmża","it":"Chełmża","ru":"Хелмжа","uk":"Хелмжа","de":"Chełmża","es":"Chełmża","en":"Chełmża","fr":"Chełmża"}},{"country":"PL","name":"Chełmno","admin1Code":"PL.73","latitude":53.34855,"longitude":18.4251,"translations":{"pt":"Chełmno","it":"Chełmno","ru":"Хелмно","uk":"Хелмно","de":"Chełmno","es":"Chelmno","en":"Chełmno","fr":"Chełmno"}},{"country":"PL","name":"Bytów","admin1Code":"PL.82","latitude":54.17057,"longitude":17.49187,"translations":{"pt":"Bytów","it":"Bytów","ru":"Бытув","uk":"Битів","de":"Bytów","es":"Bytów","en":"Bytów","fr":"Bytów"}},{"country":"PL","name":"Bytom","admin1Code":"PL.83","latitude":50.34802,"longitude":18.93282,"translations":{"pt":"Bytom","it":"Bytom","ru":"Бытом","uk":"Битом","de":"Bytom","es":"Bytom","en":"Bytom","fr":"Bytom"}},{"country":"PL","name":"Bydgoszcz","admin1Code":"PL.73","latitude":53.1235,"longitude":18.00762,"translations":{"pt":"Bydgoszcz","it":"Bydgoszcz","ru":"Быдгощ","uk":"Бидгощ","de":"Bydgoszcz","es":"Bydgoszcz","en":"Bydgoszcz","fr":"Bydgoszcz"}},{"country":"PL","name":"Brzeg","admin1Code":"PL.79","latitude":50.86079,"longitude":17.4674,"translations":{"pt":"Brzeg","it":"Brzeg","ru":"Бжег","uk":"Бжеґ","de":"Brzeg","es":"Brzeg","en":"Brzeg","fr":"Brzeg"}},{"country":"PL","name":"Brodnica","admin1Code":"PL.73","latitude":53.25967,"longitude":19.39653,"translations":{"pt":"Brodnica","it":"Brodnica","ru":"Бродница","uk":"Бродниця","de":"Brodnica","es":"Brodnica","en":"Brodnica","fr":"Brodnica"}},{"country":"PL","name":"Braniewo","admin1Code":"PL.85","latitude":54.37971,"longitude":19.81959,"translations":{"pt":"Braniewo","it":"Braniewo","ru":"Бранево","uk":"Бранево","de":"Braunsberg/ermland","es":"Braniewo","en":"Braniewo","fr":"Braniewo"}},{"country":"PL","name":"Bolesławiec","admin1Code":"PL.72","latitude":51.26418,"longitude":15.5697,"translations":{"pt":"Bolesławiec","it":"Bolesławiec","ru":"Болеславец","uk":"Bolesławiec","de":"Bunzlau","es":"Bolesławiec","en":"Bolesławiec","fr":"Bolesławiec"}},{"country":"PL","name":"Boguszów-gorce","admin1Code":"PL.72","latitude":50.75514,"longitude":16.20494,"translations":{"pt":"Boguszów-gorce","it":"Boguszów-gorce","ru":"Богушув-горце","uk":"Боґушув-ґорце","de":"Boguszów-gorce","es":"Boguszów-gorce","en":"Boguszów-gorce","fr":"Boguszów-gorce"}},{"country":"PL","name":"Bogatynia","admin1Code":"PL.72","latitude":50.90747,"longitude":14.95634,"translations":{"pt":"Bogatynia","it":"Bogatynia","ru":"Богатыня","uk":"Богатиня","de":"Bogatynia","es":"Bogatynia","en":"Bogatynia","fr":"Bogatynia"}},{"country":"PL","name":"Берунь","admin1Code":"PL.83","latitude":50.09,"longitude":19.09291,"translations":{"pt":"Berun'","it":"Berun'","ru":"Берунь","uk":"Берунь","de":"Berun'","es":"Berun'","en":"Berun'","fr":"Berun'"}},{"country":"PL","name":"Bielsko-biala","admin1Code":"PL.83","latitude":49.82245,"longitude":19.04686,"translations":{"pt":"Bielsko-biała","it":"Bielsko-biała","ru":"Бельско-бяла","uk":"Бельсько-бяла","de":"Bielitz-biala","es":"Bielsko-biała","en":"Bielsko-biala","fr":"Bielsko-biała"}},{"country":"PL","name":"Белява","admin1Code":"PL.72","latitude":50.69075,"longitude":16.623,"translations":{"pt":"Beljava","it":"Beljava","ru":"Белява","uk":"Белява","de":"Beljava","es":"Beljava","en":"Beljava","fr":"Beljava"}},{"country":"PL","name":"Białogard","admin1Code":"PL.87","latitude":54.00696,"longitude":15.98751,"translations":{"pt":"Białogard","it":"Białogard","ru":"Бялогард","uk":"Білоґард","de":"Białogard","es":"Białogard","en":"Białogard","fr":"Białogard"}},{"country":"PL","name":"Bełchatów","admin1Code":"PL.74","latitude":51.36883,"longitude":19.35671,"translations":{"pt":"Bełchatów","it":"Bełchatów","ru":"Белхатув","uk":"Белхатув","de":"Bełchatów","es":"Bełchatów","en":"Bełchatów","fr":"Bełchatów"}},{"country":"PL","name":"Będzin","admin1Code":"PL.83","latitude":50.32607,"longitude":19.12565,"translations":{"pt":"Będzin","it":"Będzin","ru":"Бендзин","uk":"Бендзин","de":"Będzin","es":"Będzin","en":"Będzin","fr":"Będzin"}},{"country":"PL","name":"Андрихув","admin1Code":"PL.77","latitude":49.85497,"longitude":19.33834,"translations":{"pt":"Andrykhuv","it":"Andrykhuv","ru":"Андрыхув","uk":"Андрихув","de":"Andrychow","es":"Andrykhuv","en":"Andrykhuv","fr":"Andrykhuv"}},{"country":"PL","name":"Aleksandrów łódzki","admin1Code":"PL.74","latitude":51.81965,"longitude":19.30384,"translations":{"pt":"Aleksandrów łódzki","it":"Aleksandrów łódzki","ru":"Александрув-лодзинский","uk":"Александрув-лодзький","de":"Aleksandrów łódzki","es":"Aleksandrów łódzki","en":"Aleksandrów łódzki","fr":"Aleksandrów łódzki"}},{"country":"PL","name":"Урсинув","admin1Code":"PL.78","latitude":52.15051,"longitude":21.05041,"translations":{"pt":"Ursynuv","it":"Ursynuv","ru":"Урсынов","uk":"Урсинув","de":"Ursynuv","es":"Ursynuv","en":"Ursynuv","fr":"Ursynuv"}},{"country":"PL","name":"Praga północ","admin1Code":"PL.78","latitude":52.25443,"longitude":21.03472,"translations":{"pt":"Praga północ","it":"Praga północ","ru":"Praga północ","uk":"Praga północ","de":"Praga północ","es":"Praga północ","en":"Praga północ","fr":"Praga północ"}},{"country":"PL","name":"Praga południe","admin1Code":"PL.78","latitude":52.24424,"longitude":21.08545,"translations":{"pt":"Praga południe","it":"Praga południe","ru":"Praga południe","uk":"Praga południe","de":"Praga południe","es":"Praga południe","en":"Praga południe","fr":"Praga południe"}},{"country":"PL","name":"Jelcz laskowice","admin1Code":"PL.72","latitude":51.02134,"longitude":17.31649,"translations":{"pt":"Jelcz laskowice","it":"Jelcz laskowice","ru":"Jelcz laskowice","uk":"Jelcz laskowice","de":"Jelcz laskowice","es":"Jelcz laskowice","en":"Jelcz laskowice","fr":"Jelcz laskowice"}},{"country":"PL","name":"Chełm","admin1Code":"PL.82","latitude":54.34048,"longitude":18.61925,"translations":{"pt":"Chełm","it":"Chełm","ru":"Chełm","uk":"Chełm","de":"Chełm","es":"Chełm","en":"Chełm","fr":"Chełm"}},{"country":"PL","name":"Piecki-migowo","admin1Code":"PL.82","latitude":54.35698,"longitude":18.58174,"translations":{"pt":"Piecki-migowo","it":"Piecki-migowo","ru":"Piecki-migowo","uk":"Piecki-migowo","de":"Piecki-migowo","es":"Piecki-migowo","en":"Piecki-migowo","fr":"Piecki-migowo"}},{"country":"PL","name":"Przymorze wielkie","admin1Code":"PL.82","latitude":54.41166,"longitude":18.5984,"translations":{"pt":"Przymorze wielkie","it":"Przymorze wielkie","ru":"Przymorze wielkie","uk":"Przymorze wielkie","de":"Przymorze wielkie","es":"Przymorze wielkie","en":"Przymorze wielkie","fr":"Przymorze wielkie"}},{"country":"PL","name":"Środmieście","admin1Code":"PL.82","latitude":54.35048,"longitude":18.65556,"translations":{"pt":"Środmieście","it":"Środmieście","ru":"Środmieście","uk":"Środmieście","de":"Środmieście","es":"Środmieście","en":"Środmieście","fr":"Środmieście"}},{"country":"PL","name":"Ujeścisko-łostowice","admin1Code":"PL.82","latitude":54.32435,"longitude":18.60269,"translations":{"pt":"Ujeścisko-łostowice","it":"Ujeścisko-łostowice","ru":"Ujeścisko-łostowice","uk":"Ujeścisko-łostowice","de":"Ujeścisko-łostowice","es":"Ujeścisko-łostowice","en":"Ujeścisko-łostowice","fr":"Ujeścisko-łostowice"}},{"country":"PL","name":"Wrzeszcz dolny","admin1Code":"PL.82","latitude":54.38473,"longitude":18.61273,"translations":{"pt":"Wrzeszcz dolny","it":"Wrzeszcz dolny","ru":"Wrzeszcz dolny","uk":"Wrzeszcz dolny","de":"Wrzeszcz dolny","es":"Wrzeszcz dolny","en":"Wrzeszcz dolny","fr":"Wrzeszcz dolny"}},{"country":"PL","name":"Wrzeszcz górny","admin1Code":"PL.82","latitude":54.37978,"longitude":18.59539,"translations":{"pt":"Wrzeszcz górny","it":"Wrzeszcz górny","ru":"Wrzeszcz górny","uk":"Wrzeszcz górny","de":"Wrzeszcz górny","es":"Wrzeszcz górny","en":"Wrzeszcz górny","fr":"Wrzeszcz górny"}},{"country":"PL","name":"Drzetowo-grabowo","admin1Code":"PL.87","latitude":53.44888,"longitude":14.5792,"translations":{"pt":"Drzetowo-grabowo","it":"Drzetowo-grabowo","ru":"Drzetowo-grabowo","uk":"Drzetowo-grabowo","de":"Drzetowo-grabowo","es":"Drzetowo-grabowo","en":"Drzetowo-grabowo","fr":"Drzetowo-grabowo"}},{"country":"PL","name":"Schwarzow","admin1Code":"PL.87","latitude":53.4273,"longitude":14.51303,"translations":{"pt":"Schwarzow","it":"Schwarzow","ru":"Schwarzow","uk":"Schwarzow","de":"Schwarzow","es":"Schwarzow","en":"Schwarzow","fr":"Schwarzow"}},{"country":"PL","name":"Osiedle kosmonautów","admin1Code":"PL.72","latitude":51.12753,"longitude":16.96186,"translations":{"pt":"Osiedle kosmonautów","it":"Osiedle kosmonautów","ru":"Osiedle kosmonautów","uk":"Osiedle kosmonautów","de":"Osiedle kosmonautów","es":"Osiedle kosmonautów","en":"Osiedle kosmonautów","fr":"Osiedle kosmonautów"}},{"country":"PL","name":"Rejon placu grunwaldzkiego","admin1Code":"PL.72","latitude":51.11669,"longitude":17.06126,"translations":{"pt":"Rejon placu grunwaldzkiego","it":"Rejon placu grunwaldzkiego","ru":"Rejon placu grunwaldzkiego","uk":"Rejon placu grunwaldzkiego","de":"Rejon placu grunwaldzkiego","es":"Rejon placu grunwaldzkiego","en":"Rejon placu grunwaldzkiego","fr":"Rejon placu grunwaldzkiego"}},{"country":"PL","name":"Rejon ulicy traugutta","admin1Code":"PL.72","latitude":51.10247,"longitude":17.04827,"translations":{"pt":"Rejon ulicy traugutta","it":"Rejon ulicy traugutta","ru":"Rejon ulicy traugutta","uk":"Rejon ulicy traugutta","de":"Rejon ulicy traugutta","es":"Rejon ulicy traugutta","en":"Rejon ulicy traugutta","fr":"Rejon ulicy traugutta"}},{"country":"PL","name":"Kozanów","admin1Code":"PL.72","latitude":51.14447,"longitude":16.96937,"translations":{"pt":"Kozanów","it":"Kozanów","ru":"Kozanów","uk":"Kozanów","de":"Kozanów","es":"Kozanów","en":"Kozanów","fr":"Kozanów"}},{"country":"PL","name":"Rejon placu świętego macieja","admin1Code":"PL.72","latitude":51.12056,"longitude":17.03761,"translations":{"pt":"Rejon placu świętego macieja","it":"Rejon placu świętego macieja","ru":"Rejon placu świętego macieja","uk":"Rejon placu świętego macieja","de":"Rejon placu świętego macieja","es":"Rejon placu świętego macieja","en":"Rejon placu świętego macieja","fr":"Rejon placu świętego macieja"}},{"country":"PL","name":"Różanka-polanka","admin1Code":"PL.72","latitude":51.14344,"longitude":17.01987,"translations":{"pt":"Różanka-polanka","it":"Różanka-polanka","ru":"Różanka-polanka","uk":"Różanka-polanka","de":"Różanka-polanka","es":"Różanka-polanka","en":"Różanka-polanka","fr":"Różanka-polanka"}},{"country":"PL","name":"Higher orunia and gdańsk south","admin1Code":"PL.82","latitude":54.32491,"longitude":18.61567,"translations":{"pt":"Higher orunia and gdańsk south","it":"Higher orunia and gdańsk south","ru":"Higher orunia and gdańsk south","uk":"Higher orunia and gdańsk south","de":"Higher orunia and gdańsk south","es":"Higher orunia and gdańsk south","en":"Higher orunia and gdańsk south","fr":"Higher orunia and gdańsk south"}}]